Workbook

Sheet Summary
A1: PT Everest Selera Muda - Fraud Investigation Workpapers
A2: Built on the participant data pack. Original 6 sheets are untouched; analysis sheets (A-H, Red Flags, Conclusion) are formula-driven. Blue = input, black = formula.
A4: Key metric | B4: Value
A5: Franchise fees per agreements (IDR) | B5: =SUM('Franchise Register'!H2:H41) -> 26930000000
A6: Bank receipts (IDR) | B6: =SUM('Incoming Transactions'!J2:J41) -> 26930000000
A7: Receipt reconciliation: amount differences | B7: ='B-Receipt Recon'!F51 -> 0
A8: Receipts dated before agreement | B8: ='B-Receipt Recon'!F48 -> 21
A9: Receipts later than due date | B9: ='B-Receipt Recon'!F49 -> 16
A10: Total outgoing (IDR) | B10: ='C-Outgoing Analysis'!H42 -> 20080000000
A11: Suspected fraud (IDR) | B11: ='H-Classification'!C5 -> 13000000000
A12: Unresolved (IDR) | B12: ='H-Classification'!C6+'H-Classification'!C7 -> 5080000000
A13: Legitimate provisional (IDR) | B13: ='H-Classification'!C8 -> 2000000000
A14: RNS share of outgoing | B14: ='D-Fund Tracing'!D5 -> 0.67231076
A15: Payments with maker=checker=approver | B15: ='H-Classification'!C13 -> 30
A16: All tie-out checks pass? | B16: =IF(COUNTIF('A-Tie-Out'!E5:E14,"PASS")=10,"YES","NO") -> YES
A19: Sheet guide
A20: A-Tie-Out | B20: Mathematical tie-out across all datasets
A21: B-Receipt Recon | B21: Q2 fee entitlement vs bank receipts
A22: C-Outgoing Analysis | B22: Q3/5/6 joined master with evidence & authorization tests
A23: D-Fund Tracing | B23: Q4 beneficiary/account tracing
A24: H-Classification | B24: Q7 legitimate / unresolved / suspected fraud
A25: Red Flags | B25: Q1 register
A26: Conclusion & Recs | B26: Q7-Q9
A27: Ref - Booklet Data | B27: Vendor master & bank change log transcribed from booklet (blue inputs)
A29: Limitations: approval matrix, user master, EV-01..08 documents not provided; classification is based on documentation in the data pack only.

Sheet A-Tie-Out
A1: A. Mathematical tie-out
A2: Every check compares two independently derived totals; PASS/FAIL is formula-driven.
A4: Check | B4: Value 1 | C4: Value 2 | D4: Difference | E4: Result
A5: Register fee total = Agreement Details fee total | B5: =SUM('Franchise Register'!H2:H41) -> 26930000000 | C5: =SUM('Agreement Details'!G2:G41) -> 26930000000 | D5: =B5-C5 -> 0 | E5: =IF(D5=0,"PASS","FAIL") -> PASS
A6: Agreement fee total = Incoming total | B6: =SUM('Agreement Details'!G2:G41) -> 26930000000 | C6: =SUM('Incoming Transactions'!J2:J41) -> 26930000000 | D6: =B6-C6 -> 0 | E6: =IF(D6=0,"PASS","FAIL") -> PASS
A7: Incoming by account (BX+BY) = Incoming total | B7: ='D-Fund Tracing'!B22 -> 26930000000 | C7: =SUM('Incoming Transactions'!J2:J41) -> 26930000000 | D7: =B7-C7 -> 0 | E7: =IF(D7=0,"PASS","FAIL") -> PASS
A8: Register # agreements = # incoming receipts | B8: =COUNTA('Franchise Register'!C2:C41) -> 40 | C8: =COUNTA('Incoming Transactions'!I2:I41) -> 40 | D8: =B8-C8 -> 0 | E8: =IF(D8=0,"PASS","FAIL") -> PASS
A9: Outgoing # (sheet) = # in Evidence = # in Approval | B9: =COUNTA('Outgoing Transactions'!B2:B38) -> 37 | C9: =COUNTA('Transaction Evidence'!A2:A38) -> 37 | D9: =B9-C9 -> 0 | E9: =IF(D9=0,"PASS","FAIL") -> PASS
A10: Evidence total = Approval total | B10: =SUM('Transaction Evidence'!D2:D38) -> 20080000000 | C10: =SUM('Payment Approval'!C2:C38) -> 20080000000 | D10: =B10-C10 -> 0 | E10: =IF(D10=0,"PASS","FAIL") -> PASS
A11: Analysis master total = Evidence total | B11: ='C-Outgoing Analysis'!H42 -> 20080000000 | C11: =SUM('Transaction Evidence'!D2:D38) -> 20080000000 | D11: =B11-C11 -> 0 | E11: =IF(D11=0,"PASS","FAIL") -> PASS
A12: Beneficiary summary = master total | B12: ='D-Fund Tracing'!C15 -> 20080000000 | C12: ='C-Outgoing Analysis'!H42 -> 20080000000 | D12: =B12-C12 -> 0 | E12: =IF(D12=0,"PASS","FAIL") -> PASS
A13: Classification total = master total | B13: ='H-Classification'!C9 -> 20080000000 | C13: ='C-Outgoing Analysis'!H42 -> 20080000000 | D13: =B13-C13 -> 0 | E13: =IF(D13=0,"PASS","FAIL") -> PASS
A14: Receipt recon: amount differences = 0 | B14: ='B-Receipt Recon'!F51 -> 0 | C14: 0 | D14: =B14-C14 -> 0 | E14: =IF(D14=0,"PASS","FAIL") -> PASS
A17: Cash position (indicative only - no opening balance provided)
A18: Total incoming | B18: =SUM('Incoming Transactions'!J2:J41) -> 26930000000
A19: Total outgoing | B19: ='C-Outgoing Analysis'!H42 -> 20080000000
A20: Net | B20: =B18-B19 -> 6850000000
A21: Outgoing as % of incoming | B21: =B19/B18 -> 0.74563684

Sheet B-Receipt Recon
A1: B. Franchise fee entitlement vs bank receipts (Q2)
A2: One row per agreement. Register, Agreement Details and Incoming Transactions are matched on Agreement ID.
A4: Agreement ID | B4: Partner | C4: Fee per Register | D4: Fee per Agreement | E4: Receipt Txn ID | F4: Receipt Amount | G4: Receipt Account | H4: Official Account | I4: Amount Diff (Receipt - Fee) | J4: Register vs Agreement Fee | K4: Account Check | L4: Sender Check | M4: Agreement Date | N4: Due Date | O4: Receipt Date | P4: Days vs Due (+ = late) | Q4: Timing Flag
A5: ='Franchise Register'!C2 -> AGR-001 | B5: ='Franchise Register'!D2 -> Partner 01 | C5: ='Franchise Register'!H2 -> 650000000 | D5: =INDEX('Agreement Details'!$G$2:$G$41,MATCH($A5,'Agreement Details'!$B$2:$B$41,0)) -> 650000000 | E5: =INDEX('Incoming Transactions'!$B$2:$B$41,MATCH($A5,'Incoming Transactions'!$I$2:$I$41,0)) -> ESM-IN-001 | F5: =INDEX('Incoming Transactions'!$J$2:$J$41,MATCH($A5,'Incoming Transactions'!$I$2:$I$41,0)) -> 650000000 | G5: =INDEX('Incoming Transactions'!$D$2:$D$41,MATCH($A5,'Incoming Transactions'!$I$2:$I$41,0)) -> ESM-BX-01 | H5: ='Franchise Register'!I2 -> ESM-BX-01 | I5: =F5-C5 -> 0 | J5: =IF(C5=D5,"OK","DIFF") -> OK | K5: =IF(G5=H5,"OK","WRONG ACCOUNT") -> OK | L5: =IF(INDEX('Incoming Transactions'!$F$2:$F$41,MATCH($A5,'Incoming Transactions'!$I$2:$I$41,0))=B5,"OK","NAME DIFF") -> OK | M5: =DATEVALUE('Franchise Register'!G2) -> 44929 | N5: =DATEVALUE('Franchise Register'!K2) -> 44959 | O5: =DATEVALUE(INDEX('Incoming Transactions'!$C$2:$C$41,MATCH($A5,'Incoming Transactions'!$I$2:$I$41,0))) -> 44960 | P5: =O5-N5 -> 1 | Q5: =IF(O5<M5,"Received BEFORE agreement date",IF(O5>N5,"Late vs due date","On time")) -> Late vs due date
A6: ='Franchise Register'!C3 -> AGR-002 | B6: ='Franchise Register'!D3 -> Partner 02 | C6: ='Franchise Register'!H3 -> 720000000 | D6: =INDEX('Agreement Details'!$G$2:$G$41,MATCH($A6,'Agreement Details'!$B$2:$B$41,0)) -> 720000000 | E6: =INDEX('Incoming Transactions'!$B$2:$B$41,MATCH($A6,'Incoming Transactions'!$I$2:$I$41,0)) -> ESM-IN-002 | F6: =INDEX('Incoming Transactions'!$J$2:$J$41,MATCH($A6,'Incoming Transactions'!$I$2:$I$41,0)) -> 720000000 | G6: =INDEX('Incoming Transactions'!$D$2:$D$41,MATCH($A6,'Incoming Transactions'!$I$2:$I$41,0)) -> ESM-BY-01 | H6: ='Franchise Register'!I3 -> ESM-BY-01 | I6: =F6-C6 -> 0 | J6: =IF(C6=D6,"OK","DIFF") -> OK | K6: =IF(G6=H6,"OK","WRONG ACCOUNT") -> OK | L6: =IF(INDEX('Incoming Transactions'!$F$2:$F$41,MATCH($A6,'Incoming Transactions'!$I$2:$I$41,0))=B6,"OK","NAME DIFF") -> OK | M6: =DATEVALUE('Franchise Register'!G3) -> 44963 | N6: =DATEVALUE('Franchise Register'!K3) -> 44993 | O6: =DATEVALUE(INDEX('Incoming Transactions'!$C$2:$C$41,MATCH($A6,'Incoming Transactions'!$I$2:$I$41,0))) -> 44967 | P6: =O6-N6 -> -26 | Q6: =IF(O6<M6,"Received BEFORE agreement date",IF(O6>N6,"Late vs due date","On time")) -> On time
A7: ='Franchise Register'!C4 -> AGR-003 | B7: ='Franchise Register'!D4 -> Partner 03 | C7: ='Franchise Register'!H4 -> 540000000 | D7: =INDEX('Agreement Details'!$G$2:$G$41,MATCH($A7,'Agreement Details'!$B$2:$B$41,0)) -> 540000000 | E7: =INDEX('Incoming Transactions'!$B$2:$B$41,MATCH($A7,'Incoming Transactions'!$I$2:$I$41,0)) -> ESM-IN-003 | F7: =INDEX('Incoming Transactions'!$J$2:$J$41,MATCH($A7,'Incoming Transactions'!$I$2:$I$41,0)) -> 540000000 | G7: =INDEX('Incoming Transactions'!$D$2:$D$41,MATCH($A7,'Incoming Transactions'!$I$2:$I$41,0)) -> ESM-BX-01 | H7: ='Franchise Register'!I4 -> ESM-BX-01 | I7: =F7-C7 -> 0 | J7: =IF(C7=D7,"OK","DIFF") -> OK | K7: =IF(G7=H7,"OK","WRONG ACCOUNT") -> OK | L7: =IF(INDEX('Incoming Transactions'!$F$2:$F$41,MATCH($A7,'Incoming Transactions'!$I$2:$I$41,0))=B7,"OK","NAME DIFF") -> OK | M7: =DATEVALUE('Franchise Register'!G4) -> 44994 | N7: =DATEVALUE('Franchise Register'!K4) -> 45024 | O7: =DATEVALUE(INDEX('Incoming Transactions'!$C$2:$C$41,MATCH($A7,'Incoming Transactions'!$I$2:$I$41,0))) -> 44987 | P7: =O7-N7 -> -37 | Q7: =IF(O7<M7,"Received BEFORE agreement date",IF(O7>N7,"Late vs due date","On time")) -> Received BEFORE agreement date
A8: ='Franchise Register'!C5 -> AGR-004 | B8: ='Franchise Register'!D5 -> Partner 04 | C8: ='Franchise Register'!H5 -> 800000000 | D8: =INDEX('Agreement Details'!$G$2:$G$41,MATCH($A8,'Agreement Details'!$B$2:$B$41,0)) -> 800000000 | E8: =INDEX('Incoming Transactions'!$B$2:$B$41,MATCH($A8,'Incoming Transactions'!$I$2:$I$41,0)) -> ESM-IN-004 | F8: =INDEX('Incoming Transactions'!$J$2:$J$41,MATCH($A8,'Incoming Transactions'!$I$2:$I$41,0)) -> 800000000 | G8: =INDEX('Incoming Transactions'!$D$2:$D$41,MATCH($A8,'Incoming Transactions'!$I$2:$I$41,0)) -> ESM-BY-01 | H8: ='Franchise Register'!I5 -> ESM-BY-01 | I8: =F8-C8 -> 0 | J8: =IF(C8=D8,"OK","DIFF") -> OK | K8: =IF(G8=H8,"OK","WRONG ACCOUNT") -> OK | L8: =IF(INDEX('Incoming Transactions'!$F$2:$F$41,MATCH($A8,'Incoming Transactions'!$I$2:$I$41,0))=B8,"OK","NAME DIFF") -> OK | M8: =DATEVALUE('Franchise Register'!G5) -> 45028 | N8: =DATEVALUE('Franchise Register'!K5) -> 45058 | O8: =DATEVALUE(INDEX('Incoming Transactions'!$C$2:$C$41,MATCH($A8,'Incoming Transactions'!$I$2:$I$41,0))) -> 45002 | P8: =O8-N8 -> -56 | Q8: =IF(O8<M8,"Received BEFORE agreement date",IF(O8>N8,"Late vs due date","On time")) -> Received BEFORE agreement date
A9: ='Franchise Register'!C6 -> AGR-005 | B9: ='Franchise Register'!D6 -> Partner 05 | C9: ='Franchise Register'!H6 -> 610000000 | D9: =INDEX('Agreement Details'!$G$2:$G$41,MATCH($A9,'Agreement Details'!$B$2:$B$41,0)) -> 610000000 | E9: =INDEX('Incoming Transactions'!$B$2:$B$41,MATCH($A9,'Incoming Transactions'!$I$2:$I$41,0)) -> ESM-IN-005 | F9: =INDEX('Incoming Transactions'!$J$2:$J$41,MATCH($A9,'Incoming Transactions'!$I$2:$I$41,0)) -> 610000000 | G9: =INDEX('Incoming Transactions'!$D$2:$D$41,MATCH($A9,'Incoming Transactions'!$I$2:$I$41,0)) -> ESM-BX-01 | H9: ='Franchise Register'!I6 -> ESM-BX-01 | I9: =F9-C9 -> 0 | J9: =IF(C9=D9,"OK","DIFF") -> OK | K9: =IF(G9=H9,"OK","WRONG ACCOUNT") -> OK | L9: =IF(INDEX('Incoming Transactions'!$F$2:$F$41,MATCH($A9,'Incoming Transactions'!$I$2:$I$41,0))=B9,"OK","NAME DIFF") -> OK | M9: =DATEVALUE('Franchise Register'!G6) -> 45061 | N9: =DATEVALUE('Franchise Register'!K6) -> 45091 | O9: =DATEVALUE(INDEX('Incoming Transactions'!$C$2:$C$41,MATCH($A9,'Incoming Transactions'!$I$2:$I$41,0))) -> 45021 | P9: =O9-N9 -> -70 | Q9: =IF(O9<M9,"Received BEFORE agreement date",IF(O9>N9,"Late vs due date","On time")) -> Received BEFORE agreement date
A10: ='Franchise Register'!C7 -> AGR-006 | B10: ='Franchise Register'!D7 -> Partner 06 | C10: ='Franchise Register'!H7 -> 700000000 | D10: =INDEX('Agreement Details'!$G$2:$G$41,MATCH($A10,'Agreement Details'!$B$2:$B$41,0)) -> 700000000 | E10: =INDEX('Incoming Transactions'!$B$2:$B$41,MATCH($A10,'Incoming Transactions'!$I$2:$I$41,0)) -> ESM-IN-006 | F10: =INDEX('Incoming Transactions'!$J$2:$J$41,MATCH($A10,'Incoming Transactions'!$I$2:$I$41,0)) -> 700000000 | G10: =INDEX('Incoming Transactions'!$D$2:$D$41,MATCH($A10,'Incoming Transactions'!$I$2:$I$41,0)) -> ESM-BY-01 | H10: ='Franchise Register'!I7 -> ESM-BY-01 | I10: =F10-C10 -> 0 | J10: =IF(C10=D10,"OK","DIFF") -> OK | K10: =IF(G10=H10,"OK","WRONG ACCOUNT") -> OK | L10: =IF(INDEX('Incoming Transactions'!$F$2:$F$41,MATCH($A10,'Incoming Transactions'!$I$2:$I$41,0))=B10,"OK","NAME DIFF") -> OK | M10: =DATEVALUE('Franchise Register'!G7) -> 45095 | N10: =DATEVALUE('Franchise Register'!K7) -> 45125 | O10: =DATEVALUE(INDEX('Incoming Transactions'!$C$2:$C$41,MATCH($A10,'Incoming Transactions'!$I$2:$I$41,0))) -> 45035 | P10: =O10-N10 -> -90 | Q10: =IF(O10<M10,"Received BEFORE agreement date",IF(O10>N10,"Late vs due date","On time")) -> Received BEFORE agreement date
A11: ='Franchise Register'!C8 -> AGR-007 | B11: ='Franchise Register'!D8 -> Partner 07 | C11: ='Franchise Register'!H8 -> 560000000 | D11: =INDEX('Agreement Details'!$G$2:$G$41,MATCH($A11,'Agreement Details'!$B$2:$B$41,0)) -> 560000000 | E11: =INDEX('Incoming Transactions'!$B$2:$B$41,MATCH($A11,'Incoming Transactions'!$I$2:$I$41,0)) -> ESM-IN-007 | F11: =INDEX('Incoming Transactions'!$J$2:$J$41,MATCH($A11,'Incoming Transactions'!$I$2:$I$41,0)) -> 560000000 | G11: =INDEX('Incoming Transactions'!$D$2:$D$41,MATCH($A11,'Incoming Transactions'!$I$2:$I$41,0)) -> ESM-BX-01 | H11: ='Franchise Register'!I8 -> ESM-BX-01 | I11: =F11-C11 -> 0 | J11: =IF(C11=D11,"OK","DIFF") -> OK | K11: =IF(G11=H11,"OK","WRONG ACCOUNT") -> OK | L11: =IF(INDEX('Incoming Transactions'!$F$2:$F$41,MATCH($A11,'Incoming Transactions'!$I$2:$I$41,0))=B11,"OK","NAME DIFF") -> OK | M11: =DATEVALUE('Franchise Register'!G8) -> 45128 | N11: =DATEVALUE('Franchise Register'!K8) -> 45158 | O11: =DATEVALUE(INDEX('Incoming Transactions'!$C$2:$C$41,MATCH($A11,'Incoming Transactions'!$I$2:$I$41,0))) -> 45051 | P11: =O11-N11 -> -107 | Q11: =IF(O11<M11,"Received BEFORE agreement date",IF(O11>N11,"Late vs due date","On time")) -> Received BEFORE agreement date
A12: ='Franchise Register'!C9 -> AGR-008 | B12: ='Franchise Register'!D9 -> Partner 08 | C12: ='Franchise Register'!H9 -> 750000000 | D12: =INDEX('Agreement Details'!$G$2:$G$41,MATCH($A12,'Agreement Details'!$B$2:$B$41,0)) -> 750000000 | E12: =INDEX('Incoming Transactions'!$B$2:$B$41,MATCH($A12,'Incoming Transactions'!$I$2:$I$41,0)) -> ESM-IN-008 | F12: =INDEX('Incoming Transactions'!$J$2:$J$41,MATCH($A12,'Incoming Transactions'!$I$2:$I$41,0)) -> 750000000 | G12: =INDEX('Incoming Transactions'!$D$2:$D$41,MATCH($A12,'Incoming Transactions'!$I$2:$I$41,0)) -> ESM-BY-01 | H12: ='Franchise Register'!I9 -> ESM-BY-01 | I12: =F12-C12 -> 0 | J12: =IF(C12=D12,"OK","DIFF") -> OK | K12: =IF(G12=H12,"OK","WRONG ACCOUNT") -> OK | L12: =IF(INDEX('Incoming Transactions'!$F$2:$F$41,MATCH($A12,'Incoming Transactions'!$I$2:$I$41,0))=B12,"OK","NAME DIFF") -> OK | M12: =DATEVALUE('Franchise Register'!G9) -> 45162 | N12: =DATEVALUE('Franchise Register'!K9) -> 45192 | O12: =DATEVALUE(INDEX('Incoming Transactions'!$C$2:$C$41,MATCH($A12,'Incoming Transactions'!$I$2:$I$41,0))) -> 45068 | P12: =O12-N12 -> -124 | Q12: =IF(O12<M12,"Received BEFORE agreement date",IF(O12>N12,"Late vs due date","On time")) -> Received BEFORE agreement date
A13: ='Franchise Register'!C10 -> AGR-009 | B13: ='Franchise Register'!D10 -> Partner 09 | C13: ='Franchise Register'!H10 -> 630000000 | D13: =INDEX('Agreement Details'!$G$2:$G$41,MATCH($A13,'Agreement Details'!$B$2:$B$41,0)) -> 630000000 | E13: =INDEX('Incoming Transactions'!$B$2:$B$41,MATCH($A13,'Incoming Transactions'!$I$2:$I$41,0)) -> ESM-IN-009 | F13: =INDEX('Incoming Transactions'!$J$2:$J$41,MATCH($A13,'Incoming Transactions'!$I$2:$I$41,0)) -> 630000000 | G13: =INDEX('Incoming Transactions'!$D$2:$D$41,MATCH($A13,'Incoming Transactions'!$I$2:$I$41,0)) -> ESM-BX-01 | H13: ='Franchise Register'!I10 -> ESM-BX-01 | I13: =F13-C13 -> 0 | J13: =IF(C13=D13,"OK","DIFF") -> OK | K13: =IF(G13=H13,"OK","WRONG ACCOUNT") -> OK | L13: =IF(INDEX('Incoming Transactions'!$F$2:$F$41,MATCH($A13,'Incoming Transactions'!$I$2:$I$41,0))=B13,"OK","NAME DIFF") -> OK | M13: =DATEVALUE('Franchise Register'!G10) -> 45171 | N13: =DATEVALUE('Franchise Register'!K10) -> 45201 | O13: =DATEVALUE(INDEX('Incoming Transactions'!$C$2:$C$41,MATCH($A13,'Incoming Transactions'!$I$2:$I$41,0))) -> 45085 | P13: =O13-N13 -> -116 | Q13: =IF(O13<M13,"Received BEFORE agreement date",IF(O13>N13,"Late vs due date","On time")) -> Received BEFORE agreement date
A14: ='Franchise Register'!C11 -> AGR-010 | B14: ='Franchise Register'!D11 -> Partner 10 | C14: ='Franchise Register'!H11 -> 890000000 | D14: =INDEX('Agreement Details'!$G$2:$G$41,MATCH($A14,'Agreement Details'!$B$2:$B$41,0)) -> 890000000 | E14: =INDEX('Incoming Transactions'!$B$2:$B$41,MATCH($A14,'Incoming Transactions'!$I$2:$I$41,0)) -> ESM-IN-010 | F14: =INDEX('Incoming Transactions'!$J$2:$J$41,MATCH($A14,'Incoming Transactions'!$I$2:$I$41,0)) -> 890000000 | G14: =INDEX('Incoming Transactions'!$D$2:$D$41,MATCH($A14,'Incoming Transactions'!$I$2:$I$41,0)) -> ESM-BY-01 | H14: ='Franchise Register'!I11 -> ESM-BY-01 | I14: =F14-C14 -> 0 | J14: =IF(C14=D14,"OK","DIFF") -> OK | K14: =IF(G14=H14,"OK","WRONG ACCOUNT") -> OK | L14: =IF(INDEX('Incoming Transactions'!$F$2:$F$41,MATCH($A14,'Incoming Transactions'!$I$2:$I$41,0))=B14,"OK","NAME DIFF") -> OK | M14: =DATEVALUE('Franchise Register'!G11) -> 45204 | N14: =DATEVALUE('Franchise Register'!K11) -> 45234 | O14: =DATEVALUE(INDEX('Incoming Transactions'!$C$2:$C$41,MATCH($A14,'Incoming Transactions'!$I$2:$I$41,0))) -> 45098 | P14: =O14-N14 -> -136 | Q14: =IF(O14<M14,"Received BEFORE agreement date",IF(O14>N14,"Late vs due date","On time")) -> Received BEFORE agreement date
A15: ='Franchise Register'!C12 -> AGR-011 | B15: ='Franchise Register'!D12 -> Partner 11 | C15: ='Franchise Register'!H12 -> 700000000 | D15: =INDEX('Agreement Details'!$G$2:$G$41,MATCH($A15,'Agreement Details'!$B$2:$B$41,0)) -> 700000000 | E15: =INDEX('Incoming Transactions'!$B$2:$B$41,MATCH($A15,'Incoming Transactions'!$I$2:$I$41,0)) -> ESM-IN-011 | F15: =INDEX('Incoming Transactions'!$J$2:$J$41,MATCH($A15,'Incoming Transactions'!$I$2:$I$41,0)) -> 700000000 | G15: =INDEX('Incoming Transactions'!$D$2:$D$41,MATCH($A15,'Incoming Transactions'!$I$2:$I$41,0)) -> ESM-BX-01 | H15: ='Franchise Register'!I12 -> ESM-BX-01 | I15: =F15-C15 -> 0 | J15: =IF(C15=D15,"OK","DIFF") -> OK | K15: =IF(G15=H15,"OK","WRONG ACCOUNT") -> OK | L15: =IF(INDEX('Incoming Transactions'!$F$2:$F$41,MATCH($A15,'Incoming Transactions'!$I$2:$I$41,0))=B15,"OK","NAME DIFF") -> OK | M15: =DATEVALUE('Franchise Register'!G12) -> 45238 | N15: =DATEVALUE('Franchise Register'!K12) -> 45268 | O15: =DATEVALUE(INDEX('Incoming Transactions'!$C$2:$C$41,MATCH($A15,'Incoming Transactions'!$I$2:$I$41,0))) -> 45114 | P15: =O15-N15 -> -154 | Q15: =IF(O15<M15,"Received BEFORE agreement date",IF(O15>N15,"Late vs due date","On time")) -> Received BEFORE agreement date
A16: ='Franchise Register'!C13 -> AGR-012 | B16: ='Franchise Register'!D13 -> Partner 12 | C16: ='Franchise Register'!H13 -> 500000000 | D16: =INDEX('Agreement Details'!$G$2:$G$41,MATCH($A16,'Agreement Details'!$B$2:$B$41,0)) -> 500000000 | E16: =INDEX('Incoming Transactions'!$B$2:$B$41,MATCH($A16,'Incoming Transactions'!$I$2:$I$41,0)) -> ESM-IN-012 | F16: =INDEX('Incoming Transactions'!$J$2:$J$41,MATCH($A16,'Incoming Transactions'!$I$2:$I$41,0)) -> 500000000 | G16: =INDEX('Incoming Transactions'!$D$2:$D$41,MATCH($A16,'Incoming Transactions'!$I$2:$I$41,0)) -> ESM-BY-01 | H16: ='Franchise Register'!I13 -> ESM-BY-01 | I16: =F16-C16 -> 0 | J16: =IF(C16=D16,"OK","DIFF") -> OK | K16: =IF(G16=H16,"OK","WRONG ACCOUNT") -> OK | L16: =IF(INDEX('Incoming Transactions'!$F$2:$F$41,MATCH($A16,'Incoming Transactions'!$I$2:$I$41,0))=B16,"OK","NAME DIFF") -> OK | M16: =DATEVALUE('Franchise Register'!G13) -> 45271 | N16: =DATEVALUE('Franchise Register'!K13) -> 45301 | O16: =DATEVALUE(INDEX('Incoming Transactions'!$C$2:$C$41,MATCH($A16,'Incoming Transactions'!$I$2:$I$41,0))) -> 45128 | P16: =O16-N16 -> -173 | Q16: =IF(O16<M16,"Received BEFORE agreement date",IF(O16>N16,"Late vs due date","On time")) -> Received BEFORE agreement date
... A44: ='Franchise Register'!C41 -> AGR-040 | B44: ='Franchise Register'!D41 -> Partner 40 | C44: ='Franchise Register'!H41 -> 720000000 | D44: =INDEX('Agreement Details'!$G$2:$G$41,MATCH($A44,'Agreement Details'!$B$2:$B$41,0)) -> 720000000 | E44: =INDEX('Incoming Transactions'!$B$2:$B$41,MATCH($A44,'Incoming Transactions'!$I$2:$I$41,0)) -> ESM-IN-040 | F44: =INDEX('Incoming Transactions'!$J$2:$J$41,MATCH($A44,'Incoming Transactions'!$I$2:$I$41,0)) -> 720000000 | G44: =INDEX('Incoming Transactions'!$D$2:$D$41,MATCH($A44,'Incoming Transactions'!$I$2:$I$41,0)) -> ESM-BY-01 | H44: ='Franchise Register'!I41 -> ESM-BY-01 | I44: =F44-C44 -> 0 | J44: =IF(C44=D44,"OK","DIFF") -> OK | K44: =IF(G44=H44,"OK","WRONG ACCOUNT") -> OK | L44: =IF(INDEX('Incoming Transactions'!$F$2:$F$41,MATCH($A44,'Incoming Transactions'!$I$2:$I$41,0))=B44,"OK","NAME DIFF") -> OK | M44: =DATEVALUE('Franchise Register'!G41) -> 45402 | N44: =DATEVALUE('Franchise Register'!K41) -> 45432 | O44: =DATEVALUE(INDEX('Incoming Transactions'!$C$2:$C$41,MATCH($A44,'Incoming Transactions'!$I$2:$I$41,0))) -> 45604 | P44: =O44-N44 -> 172 | Q44: =IF(O44<M44,"Received BEFORE agreement date",IF(O44>N44,"Late vs due date","On time")) -> Late vs due date
A45: TOTAL | C45: =SUM(C5:C44) -> 26930000000 | D45: =SUM(D5:D44) -> 26930000000 | F45: =SUM(F5:F44) -> 26930000000 | I45: =SUM(I5:I44) -> 0
A47: Exception counts
A48: Received before agreement date | F48: =COUNTIF(Q5:Q44,"Received BEFORE*") -> 21
A49: Late vs due date | F49: =COUNTIF(Q5:Q44,"Late*") -> 16
A50: On time | F50: =COUNTIF(Q5:Q44,"On time") -> 3
A51: Amount differences | F51: =COUNTIF(I5:I44,"<>0") -> 0
A52: Wrong account | F52: =COUNTIF(K5:K44,"WRONG*") -> 0
A53: Max days late | F53: =MAX(P5:P44) -> 223
A54: Largest lead before agreement date (days) | F54: =SUMPRODUCT(MAX(M5:M44-O5:O44)) -> 299
A56: Reading: amounts, accounts and senders reconcile 100%; the only exceptions are timing (dates before agreement / late). "Paid in Full" in the Register does not reflect lateness.

Sheet C-Outgoing Analysis
A1: C/D/E. Outgoing transaction master: join, evidence test, authorization test, classification (Q3-Q7) | V1: Threshold (IDR) | W1: 900000000
A2: Outgoing (no amounts) joined to Transaction Evidence via Transaction ID, and to Payment Approval via Reference. All formula-driven. | V2: Assumption: approval matrix not provided; 900,000,000 is an analyst-chosen screen for "large, near-1bn" payments. Change W1 to re-run.
A4: Txn ID | B4: Date | C4: ESM Account | D4: Beneficiary | E4: Beneficiary Account | F4: Beneficiary Bank | G4: Reference | H4: Amount (IDR) | I4: Approval Description | J4: Maker | K4: Checker | L4: Approver | M4: Amount Evidence = Approval | N4: Full doc package? | O4: RNS? | P4: Maker=Checker=Approver | Q4: Amount >= threshold | R4: Account in change-log extract? | S4: Classification | T4: Evidence note (from data pack)
A5: ='Outgoing Transactions'!B2 -> ESM-OUT-001 | B5: =DATEVALUE('Outgoing Transactions'!C2) -> 45021 | C5: ='Outgoing Transactions'!D2 -> ESM-BX-01 | D5: ='Outgoing Transactions'!F2 -> PT Laut Banda Pangan | E5: ='Outgoing Transactions'!G2 -> VND-BD-01 | F5: ='Outgoing Transactions'!H2 -> Bank Samudra | G5: =INDEX('Transaction Evidence'!$B$2:$B$38,MATCH($A5,'Transaction Evidence'!$A$2:$A$38,0)) -> CTR-2024-011 | H5: =INDEX('Transaction Evidence'!$D$2:$D$38,MATCH($A5,'Transaction Evidence'!$A$2:$A$38,0)) -> 300000000 | I5: =INDEX('Payment Approval'!$E$2:$E$38,MATCH($G5,'Payment Approval'!$B$2:$B$38,0)) -> Raw material procurement | J5: =INDEX('Payment Approval'!$F$2:$F$38,MATCH($G5,'Payment Approval'!$B$2:$B$38,0)) -> USR-FIN-02 | K5: =INDEX('Payment Approval'!$G$2:$G$38,MATCH($G5,'Payment Approval'!$B$2:$B$38,0)) -> USR-FIN-02 | L5: =INDEX('Payment Approval'!$H$2:$H$38,MATCH($G5,'Payment Approval'!$B$2:$B$38,0)) -> USR-FIN-02 | M5: =IF(H5=INDEX('Payment Approval'!$C$2:$C$38,MATCH($G5,'Payment Approval'!$B$2:$B$38,0)),"OK","DIFF") -> OK | N5: =IF(ISNUMBER(SEARCH("Contract/PO/SPK; Invoice; Work",INDEX('Transaction Evidence'!$E$2:$E$38,MATCH($A5,'Transaction Evidence'!$A$2:$A$38,0)))),"Yes","No") -> Yes | O5: =IF(D5="PT Rinjani Niaga Sentosa","Yes","No") -> No | P5: =IF(AND(J5=K5,K5=L5),"Yes","No") -> Yes | Q5: =IF(H5>=$W$1,"Yes","No") -> No | R5: =IF(COUNTIF('Ref - Booklet Data'!$C$14:$C$19,E5)>0,"Registered","Not in extract") -> Registered | S5: =IF(AND(O5="Yes",N5="No"),"Suspected fraud",IF(O5="Yes","Unresolved - RNS with contract",IF(N5="Yes","Legitimate (provisional)","Unresolved - partial docs"))) -> Legitimate (provisional) | T5: =INDEX('Transaction Evidence'!$F$2:$F$38,MATCH($A5,'Transaction Evidence'!$A$2:$A$38,0)) -> Contract/PO/SPK, invoice, work/hand-over report, evidence of receipt of goods/services, and Board of Directors approval are on file for this transaction.
A6: ='Outgoing Transactions'!B3 -> ESM-OUT-002 | B6: =DATEVALUE('Outgoing Transactions'!C3) -> 45034 | C6: ='Outgoing Transactions'!D3 -> ESM-BY-01 | D6: ='Outgoing Transactions'!F3 -> PT Rinjani Niaga Sentosa | E6: ='Outgoing Transactions'!G3 -> RNS-BR-01 | F6: ='Outgoing Transactions'!H3 -> Bank Rinjani | G6: =INDEX('Transaction Evidence'!$B$2:$B$38,MATCH($A6,'Transaction Evidence'!$A$2:$A$38,0)) -> REQ-RNS-001 | H6: =INDEX('Transaction Evidence'!$D$2:$D$38,MATCH($A6,'Transaction Evidence'!$A$2:$A$38,0)) -> 920000000 | I6: =INDEX('Payment Approval'!$E$2:$E$38,MATCH($G6,'Payment Approval'!$B$2:$B$38,0)) -> Expansion cost adjustment | J6: =INDEX('Payment Approval'!$F$2:$F$38,MATCH($G6,'Payment Approval'!$B$2:$B$38,0)) -> USR-FIN-02 | K6: =INDEX('Payment Approval'!$G$2:$G$38,MATCH($G6,'Payment Approval'!$B$2:$B$38,0)) -> USR-FIN-02 | L6: =INDEX('Payment Approval'!$H$2:$H$38,MATCH($G6,'Payment Approval'!$B$2:$B$38,0)) -> USR-FIN-02 | M6: =IF(H6=INDEX('Payment Approval'!$C$2:$C$38,MATCH($G6,'Payment Approval'!$B$2:$B$38,0)),"OK","DIFF") -> OK | N6: =IF(ISNUMBER(SEARCH("Contract/PO/SPK; Invoice; Work",INDEX('Transaction Evidence'!$E$2:$E$38,MATCH($A6,'Transaction Evidence'!$A$2:$A$38,0)))),"Yes","No") -> No | O6: =IF(D6="PT Rinjani Niaga Sentosa","Yes","No") -> Yes | P6: =IF(AND(J6=K6,K6=L6),"Yes","No") -> Yes | Q6: =IF(H6>=$W$1,"Yes","No") -> Yes | R6: =IF(COUNTIF('Ref - Booklet Data'!$C$14:$C$19,E6)>0,"Registered","Not in extract") -> Registered | S6: =IF(AND(O6="Yes",N6="No"),"Suspected fraud",IF(O6="Yes","Unresolved - RNS with contract",IF(N6="Yes","Legitimate (provisional)","Unresolved - partial docs"))) -> Suspected fraud | T6: =INDEX('Transaction Evidence'!$F$2:$F$38,MATCH($A6,'Transaction Evidence'!$A$2:$A$38,0)) -> Only a Payment Request, transfer evidence, and email/internal instructions are on file for this transaction. No contract, PO/SPK, work/delivery report, or evidence of
A7: ='Outgoing Transactions'!B4 -> ESM-OUT-003 | B7: =DATEVALUE('Outgoing Transactions'!C4) -> 45057 | C7: ='Outgoing Transactions'!D4 -> ESM-BX-01 | D7: ='Outgoing Transactions'!F4 -> PT Rinjani Niaga Sentosa | E7: ='Outgoing Transactions'!G4 -> RNS-BR-01 | F7: ='Outgoing Transactions'!H4 -> Bank Rinjani | G7: =INDEX('Transaction Evidence'!$B$2:$B$38,MATCH($A7,'Transaction Evidence'!$A$2:$A$38,0)) -> REQ-RNS-015 | H7: =INDEX('Transaction Evidence'!$D$2:$D$38,MATCH($A7,'Transaction Evidence'!$A$2:$A$38,0)) -> 975000000 | I7: =INDEX('Payment Approval'!$E$2:$E$38,MATCH($G7,'Payment Approval'!$B$2:$B$38,0)) -> Project fund adjustment | J7: =INDEX('Payment Approval'!$F$2:$F$38,MATCH($G7,'Payment Approval'!$B$2:$B$38,0)) -> USR-FIN-02 | K7: =INDEX('Payment Approval'!$G$2:$G$38,MATCH($G7,'Payment Approval'!$B$2:$B$38,0)) -> USR-FIN-02 | L7: =INDEX('Payment Approval'!$H$2:$H$38,MATCH($G7,'Payment Approval'!$B$2:$B$38,0)) -> USR-FIN-02 | M7: =IF(H7=INDEX('Payment Approval'!$C$2:$C$38,MATCH($G7,'Payment Approval'!$B$2:$B$38,0)),"OK","DIFF") -> OK | N7: =IF(ISNUMBER(SEARCH("Contract/PO/SPK; Invoice; Work",INDEX('Transaction Evidence'!$E$2:$E$38,MATCH($A7,'Transaction Evidence'!$A$2:$A$38,0)))),"Yes","No") -> No | O7: =IF(D7="PT Rinjani Niaga Sentosa","Yes","No") -> Yes | P7: =IF(AND(J7=K7,K7=L7),"Yes","No") -> Yes | Q7: =IF(H7>=$W$1,"Yes","No") -> Yes | R7: =IF(COUNTIF('Ref - Booklet Data'!$C$14:$C$19,E7)>0,"Registered","Not in extract") -> Registered | S7: =IF(AND(O7="Yes",N7="No"),"Suspected fraud",IF(O7="Yes","Unresolved - RNS with contract",IF(N7="Yes","Legitimate (provisional)","Unresolved - partial docs"))) -> Suspected fraud | T7: =INDEX('Transaction Evidence'!$F$2:$F$38,MATCH($A7,'Transaction Evidence'!$A$2:$A$38,0)) -> Only a Payment Request, transfer evidence, and email/internal instructions are on file for this transaction. No contract, PO/SPK, work/delivery report, or evidence of
A8: ='Outgoing Transactions'!B5 -> ESM-OUT-004 | B8: =DATEVALUE('Outgoing Transactions'!C5) -> 45084 | C8: ='Outgoing Transactions'!D5 -> ESM-BY-01 | D8: ='Outgoing Transactions'!F5 -> PT Laut Natuna Jasa | E8: ='Outgoing Transactions'!G5 -> VND-JS-02 | F8: ='Outgoing Transactions'!H5 -> Bank Nusantara | G8: =INDEX('Transaction Evidence'!$B$2:$B$38,MATCH($A8,'Transaction Evidence'!$A$2:$A$38,0)) -> CTR-2024-057 | H8: =INDEX('Transaction Evidence'!$D$2:$D$38,MATCH($A8,'Transaction Evidence'!$A$2:$A$38,0)) -> 50000000 | I8: =INDEX('Payment Approval'!$E$2:$E$38,MATCH($G8,'Payment Approval'!$B$2:$B$38,0)) -> Operational support | J8: =INDEX('Payment Approval'!$F$2:$F$38,MATCH($G8,'Payment Approval'!$B$2:$B$38,0)) -> USR-FIN-01 | K8: =INDEX('Payment Approval'!$G$2:$G$38,MATCH($G8,'Payment Approval'!$B$2:$B$38,0)) -> USR-FIN-02 | L8: =INDEX('Payment Approval'!$H$2:$H$38,MATCH($G8,'Payment Approval'!$B$2:$B$38,0)) -> USR-FIN-02 | M8: =IF(H8=INDEX('Payment Approval'!$C$2:$C$38,MATCH($G8,'Payment Approval'!$B$2:$B$38,0)),"OK","DIFF") -> OK | N8: =IF(ISNUMBER(SEARCH("Contract/PO/SPK; Invoice; Work",INDEX('Transaction Evidence'!$E$2:$E$38,MATCH($A8,'Transaction Evidence'!$A$2:$A$38,0)))),"Yes","No") -> Yes | O8: =IF(D8="PT Rinjani Niaga Sentosa","Yes","No") -> No | P8: =IF(AND(J8=K8,K8=L8),"Yes","No") -> No | Q8: =IF(H8>=$W$1,"Yes","No") -> No | R8: =IF(COUNTIF('Ref - Booklet Data'!$C$14:$C$19,E8)>0,"Registered","Not in extract") -> Not in extract | S8: =IF(AND(O8="Yes",N8="No"),"Suspected fraud",IF(O8="Yes","Unresolved - RNS with contract",IF(N8="Yes","Legitimate (provisional)","Unresolved - partial docs"))) -> Legitimate (provisional) | T8: =INDEX('Transaction Evidence'!$F$2:$F$38,MATCH($A8,'Transaction Evidence'!$A$2:$A$38,0)) -> Contract/PO/SPK, invoice, work/hand-over report, evidence of receipt of goods/services, and Board of Directors approval are on file for this transaction.
A9: ='Outgoing Transactions'!B6 -> ESM-OUT-005 | B9: =DATEVALUE('Outgoing Transactions'!C6) -> 45106 | C9: ='Outgoing Transactions'!D6 -> ESM-BX-01 | D9: ='Outgoing Transactions'!F6 -> PT Laut Seram Konsultan | E9: ='Outgoing Transactions'!G6 -> VND-KS-01 | F9: ='Outgoing Transactions'!H6 -> Bank Cakra | G9: =INDEX('Transaction Evidence'!$B$2:$B$38,MATCH($A9,'Transaction Evidence'!$A$2:$A$38,0)) -> INV-LS-2404A | H9: =INDEX('Transaction Evidence'!$D$2:$D$38,MATCH($A9,'Transaction Evidence'!$A$2:$A$38,0)) -> 450000000 | I9: =INDEX('Payment Approval'!$E$2:$E$38,MATCH($G9,'Payment Approval'!$B$2:$B$38,0)) -> Development consulting services | J9: =INDEX('Payment Approval'!$F$2:$F$38,MATCH($G9,'Payment Approval'!$B$2:$B$38,0)) -> USR-FIN-02 | K9: =INDEX('Payment Approval'!$G$2:$G$38,MATCH($G9,'Payment Approval'!$B$2:$B$38,0)) -> USR-FIN-02 | L9: =INDEX('Payment Approval'!$H$2:$H$38,MATCH($G9,'Payment Approval'!$B$2:$B$38,0)) -> USR-FIN-02 | M9: =IF(H9=INDEX('Payment Approval'!$C$2:$C$38,MATCH($G9,'Payment Approval'!$B$2:$B$38,0)),"OK","DIFF") -> OK | N9: =IF(ISNUMBER(SEARCH("Contract/PO/SPK; Invoice; Work",INDEX('Transaction Evidence'!$E$2:$E$38,MATCH($A9,'Transaction Evidence'!$A$2:$A$38,0)))),"Yes","No") -> No | O9: =IF(D9="PT Rinjani Niaga Sentosa","Yes","No") -> No | P9: =IF(AND(J9=K9,K9=L9),"Yes","No") -> Yes | Q9: =IF(H9>=$W$1,"Yes","No") -> No | R9: =IF(COUNTIF('Ref - Booklet Data'!$C$14:$C$19,E9)>0,"Registered","Not in extract") -> Not in extract | S9: =IF(AND(O9="Yes",N9="No"),"Suspected fraud",IF(O9="Yes","Unresolved - RNS with contract",IF(N9="Yes","Legitimate (provisional)","Unresolved - partial docs"))) -> Unresolved - partial docs | T9: =INDEX('Transaction Evidence'!$F$2:$F$38,MATCH($A9,'Transaction Evidence'!$A$2:$A$38,0)) -> Only an invoice is on file for this transaction. No contract/SPK, work report, or evidence of receipt of services was located.
A10: ='Outgoing Transactions'!B7 -> ESM-OUT-006 | B10: =DATEVALUE('Outgoing Transactions'!C7) -> 45106 | C10: ='Outgoing Transactions'!D7 -> ESM-BY-01 | D10: ='Outgoing Transactions'!F7 -> PT Rinjani Niaga Sentosa | E10: ='Outgoing Transactions'!G7 -> RNS-BR-01 | F10: ='Outgoing Transactions'!H7 -> Bank Rinjani | G10: =INDEX('Transaction Evidence'!$B$2:$B$38,MATCH($A10,'Transaction Evidence'!$A$2:$A$38,0)) -> REQ-RNS-007 | H10: =INDEX('Transaction Evidence'!$D$2:$D$38,MATCH($A10,'Transaction Evidence'!$A$2:$A$38,0)) -> 900000000 | I10: =INDEX('Payment Approval'!$E$2:$E$38,MATCH($G10,'Payment Approval'!$B$2:$B$38,0)) -> Expansion needs management | J10: =INDEX('Payment Approval'!$F$2:$F$38,MATCH($G10,'Payment Approval'!$B$2:$B$38,0)) -> USR-FIN-02 | K10: =INDEX('Payment Approval'!$G$2:$G$38,MATCH($G10,'Payment Approval'!$B$2:$B$38,0)) -> USR-FIN-02 | L10: =INDEX('Payment Approval'!$H$2:$H$38,MATCH($G10,'Payment Approval'!$B$2:$B$38,0)) -> USR-FIN-02 | M10: =IF(H10=INDEX('Payment Approval'!$C$2:$C$38,MATCH($G10,'Payment Approval'!$B$2:$B$38,0)),"OK","DIFF") -> OK | N10: =IF(ISNUMBER(SEARCH("Contract/PO/SPK; Invoice; Work",INDEX('Transaction Evidence'!$E$2:$E$38,MATCH($A10,'Transaction Evidence'!$A$2:$A$38,0)))),"Yes","No") -> No | O10: =IF(D10="PT Rinjani Niaga Sentosa","Yes","No") -> Yes | P10: =IF(AND(J10=K10,K10=L10),"Yes","No") -> Yes | Q10: =IF(H10>=$W$1,"Yes","No") -> Yes | R10: =IF(COUNTIF('Ref - Booklet Data'!$C$14:$C$19,E10)>0,"Registered","Not in extract") -> Registered | S10: =IF(AND(O10="Yes",N10="No"),"Suspected fraud",IF(O10="Yes","Unresolved - RNS with contract",IF(N10="Yes","Legitimate (provisional)","Unresolved - partial docs"))) -> Suspected fraud | T10: =INDEX('Transaction Evidence'!$F$2:$F$38,MATCH($A10,'Transaction Evidence'!$A$2:$A$38,0)) -> Only a Payment Request, transfer evidence, and email/internal instructions are on file for this transaction. No contract, PO/SPK, work/delivery report, or evidence of
A11: ='Outgoing Transactions'!B8 -> ESM-OUT-007 | B11: =DATEVALUE('Outgoing Transactions'!C8) -> 45119 | C11: ='Outgoing Transactions'!D8 -> ESM-BX-01 | D11: ='Outgoing Transactions'!F8 -> PT Rinjani Niaga Sentosa | E11: ='Outgoing Transactions'!G8 -> RNS-BR-01 | F11: ='Outgoing Transactions'!H8 -> Bank Rinjani | G11: =INDEX('Transaction Evidence'!$B$2:$B$38,MATCH($A11,'Transaction Evidence'!$A$2:$A$38,0)) -> REQ-RNS-011 | H11: =INDEX('Transaction Evidence'!$D$2:$D$38,MATCH($A11,'Transaction Evidence'!$A$2:$A$38,0)) -> 850000000 | I11: =INDEX('Payment Approval'!$E$2:$E$38,MATCH($G11,'Payment Approval'!$B$2:$B$38,0)) -> Expansion cost reimbursement | J11: =INDEX('Payment Approval'!$F$2:$F$38,MATCH($G11,'Payment Approval'!$B$2:$B$38,0)) -> USR-FIN-02 | K11: =INDEX('Payment Approval'!$G$2:$G$38,MATCH($G11,'Payment Approval'!$B$2:$B$38,0)) -> USR-FIN-02 | L11: =INDEX('Payment Approval'!$H$2:$H$38,MATCH($G11,'Payment Approval'!$B$2:$B$38,0)) -> USR-FIN-02 | M11: =IF(H11=INDEX('Payment Approval'!$C$2:$C$38,MATCH($G11,'Payment Approval'!$B$2:$B$38,0)),"OK","DIFF") -> OK | N11: =IF(ISNUMBER(SEARCH("Contract/PO/SPK; Invoice; Work",INDEX('Transaction Evidence'!$E$2:$E$38,MATCH($A11,'Transaction Evidence'!$A$2:$A$38,0)))),"Yes","No") -> No | O11: =IF(D11="PT Rinjani Niaga Sentosa","Yes","No") -> Yes | P11: =IF(AND(J11=K11,K11=L11),"Yes","No") -> Yes | Q11: =IF(H11>=$W$1,"Yes","No") -> No | R11: =IF(COUNTIF('Ref - Booklet Data'!$C$14:$C$19,E11)>0,"Registered","Not in extract") -> Registered | S11: =IF(AND(O11="Yes",N11="No"),"Suspected fraud",IF(O11="Yes","Unresolved - RNS with contract",IF(N11="Yes","Legitimate (provisional)","Unresolved - partial docs"))) -> Suspected fraud | T11: =INDEX('Transaction Evidence'!$F$2:$F$38,MATCH($A11,'Transaction Evidence'!$A$2:$A$38,0)) -> Only a Payment Request, transfer evidence, and email/internal instructions are on file for this transaction. No contract, PO/SPK, work/delivery report, or evidence of
A12: ='Outgoing Transactions'!B9 -> ESM-OUT-008 | B12: =DATEVALUE('Outgoing Transactions'!C9) -> 45153 | C12: ='Outgoing Transactions'!D9 -> ESM-BY-01 | D12: ='Outgoing Transactions'!F9 -> PT Laut Banda Pangan | E12: ='Outgoing Transactions'!G9 -> VND-BD-03 | F12: ='Outgoing Transactions'!H9 -> Bank Cakra | G12: =INDEX('Transaction Evidence'!$B$2:$B$38,MATCH($A12,'Transaction Evidence'!$A$2:$A$38,0)) -> REQ-ESM-014A | H12: =INDEX('Transaction Evidence'!$D$2:$D$38,MATCH($A12,'Transaction Evidence'!$A$2:$A$38,0)) -> 300000000 | I12: =INDEX('Payment Approval'!$E$2:$E$38,MATCH($G12,'Payment Approval'!$B$2:$B$38,0)) -> Operational outgoing | J12: =INDEX('Payment Approval'!$F$2:$F$38,MATCH($G12,'Payment Approval'!$B$2:$B$38,0)) -> USR-FIN-02 | K12: =INDEX('Payment Approval'!$G$2:$G$38,MATCH($G12,'Payment Approval'!$B$2:$B$38,0)) -> USR-FIN-02 | L12: =INDEX('Payment Approval'!$H$2:$H$38,MATCH($G12,'Payment Approval'!$B$2:$B$38,0)) -> USR-FIN-02 | M12: =IF(H12=INDEX('Payment Approval'!$C$2:$C$38,MATCH($G12,'Payment Approval'!$B$2:$B$38,0)),"OK","DIFF") -> OK | N12: =IF(ISNUMBER(SEARCH("Contract/PO/SPK; Invoice; Work",INDEX('Transaction Evidence'!$E$2:$E$38,MATCH($A12,'Transaction Evidence'!$A$2:$A$38,0)))),"Yes","No") -> No | O12: =IF(D12="PT Rinjani Niaga Sentosa","Yes","No") -> No | P12: =IF(AND(J12=K12,K12=L12),"Yes","No") -> Yes | Q12: =IF(H12>=$W$1,"Yes","No") -> No | R12: =IF(COUNTIF('Ref - Booklet Data'!$C$14:$C$19,E12)>0,"Registered","Not in extract") -> Not in extract | S12: =IF(AND(O12="Yes",N12="No"),"Suspected fraud",IF(O12="Yes","Unresolved - RNS with contract",IF(N12="Yes","Legitimate (provisional)","Unresolved - partial docs"))) -> Unresolved - partial docs | T12: =INDEX('Transaction Evidence'!$F$2:$F$38,MATCH($A12,'Transaction Evidence'!$A$2:$A$38,0)) -> Only a payment request and email instruction are on file for this transaction. No invoice or evidence of receipt of benefits was located.
A13: ='Outgoing Transactions'!B10 -> ESM-OUT-009 | B13: =DATEVALUE('Outgoing Transactions'!C10) -> 45162 | C13: ='Outgoing Transactions'!D10 -> ESM-BX-01 | D13: ='Outgoing Transactions'!F10 -> PT Rinjani Niaga Sentosa | E13: ='Outgoing Transactions'!G10 -> RNS-BR-01 | F13: ='Outgoing Transactions'!H10 -> Bank Rinjani | G13: =INDEX('Transaction Evidence'!$B$2:$B$38,MATCH($A13,'Transaction Evidence'!$A$2:$A$38,0)) -> REQ-RNS-003 | H13: =INDEX('Transaction Evidence'!$D$2:$D$38,MATCH($A13,'Transaction Evidence'!$A$2:$A$38,0)) -> 950000000 | I13: =INDEX('Payment Approval'!$E$2:$E$38,MATCH($G13,'Payment Approval'!$B$2:$B$38,0)) -> Outlet needs payment | J13: =INDEX('Payment Approval'!$F$2:$F$38,MATCH($G13,'Payment Approval'!$B$2:$B$38,0)) -> USR-FIN-02 | K13: =INDEX('Payment Approval'!$G$2:$G$38,MATCH($G13,'Payment Approval'!$B$2:$B$38,0)) -> USR-FIN-02 | L13: =INDEX('Payment Approval'!$H$2:$H$38,MATCH($G13,'Payment Approval'!$B$2:$B$38,0)) -> USR-FIN-02 | M13: =IF(H13=INDEX('Payment Approval'!$C$2:$C$38,MATCH($G13,'Payment Approval'!$B$2:$B$38,0)),"OK","DIFF") -> OK | N13: =IF(ISNUMBER(SEARCH("Contract/PO/SPK; Invoice; Work",INDEX('Transaction Evidence'!$E$2:$E$38,MATCH($A13,'Transaction Evidence'!$A$2:$A$38,0)))),"Yes","No") -> No | O13: =IF(D13="PT Rinjani Niaga Sentosa","Yes","No") -> Yes | P13: =IF(AND(J13=K13,K13=L13),"Yes","No") -> Yes | Q13: =IF(H13>=$W$1,"Yes","No") -> Yes | R13: =IF(COUNTIF('Ref - Booklet Data'!$C$14:$C$19,E13)>0,"Registered","Not in extract") -> Registered | S13: =IF(AND(O13="Yes",N13="No"),"Suspected fraud",IF(O13="Yes","Unresolved - RNS with contract",IF(N13="Yes","Legitimate (provisional)","Unresolved - partial docs"))) -> Suspected fraud | T13: =INDEX('Transaction Evidence'!$F$2:$F$38,MATCH($A13,'Transaction Evidence'!$A$2:$A$38,0)) -> Only a Payment Request, transfer evidence, and email/internal instructions are on file for this transaction. No contract, PO/SPK, work/delivery report, or evidence of
A14: ='Outgoing Transactions'!B11 -> ESM-OUT-010 | B14: =DATEVALUE('Outgoing Transactions'!C11) -> 45183 | C14: ='Outgoing Transactions'!D11 -> ESM-BY-01 | D14: ='Outgoing Transactions'!F11 -> PT Laut Seram Konsultan | E14: ='Outgoing Transactions'!G11 -> VND-KS-02 | F14: ='Outgoing Transactions'!H11 -> Bank Samudra | G14: =INDEX('Transaction Evidence'!$B$2:$B$38,MATCH($A14,'Transaction Evidence'!$A$2:$A$38,0)) -> CTR-2024-046 | H14: =INDEX('Transaction Evidence'!$D$2:$D$38,MATCH($A14,'Transaction Evidence'!$A$2:$A$38,0)) -> 200000000 | I14: =INDEX('Payment Approval'!$E$2:$E$38,MATCH($G14,'Payment Approval'!$B$2:$B$38,0)) -> Consulting services | J14: =INDEX('Payment Approval'!$F$2:$F$38,MATCH($G14,'Payment Approval'!$B$2:$B$38,0)) -> USR-FIN-01 | K14: =INDEX('Payment Approval'!$G$2:$G$38,MATCH($G14,'Payment Approval'!$B$2:$B$38,0)) -> USR-FIN-02 | L14: =INDEX('Payment Approval'!$H$2:$H$38,MATCH($G14,'Payment Approval'!$B$2:$B$38,0)) -> USR-FIN-02 | M14: =IF(H14=INDEX('Payment Approval'!$C$2:$C$38,MATCH($G14,'Payment Approval'!$B$2:$B$38,0)),"OK","DIFF") -> OK | N14: =IF(ISNUMBER(SEARCH("Contract/PO/SPK; Invoice; Work",INDEX('Transaction Evidence'!$E$2:$E$38,MATCH($A14,'Transaction Evidence'!$A$2:$A$38,0)))),"Yes","No") -> Yes | O14: =IF(D14="PT Rinjani Niaga Sentosa","Yes","No") -> No | P14: =IF(AND(J14=K14,K14=L14),"Yes","No") -> No | Q14: =IF(H14>=$W$1,"Yes","No") -> No | R14: =IF(COUNTIF('Ref - Booklet Data'!$C$14:$C$19,E14)>0,"Registered","Not in extract") -> Not in extract | S14: =IF(AND(O14="Yes",N14="No"),"Suspected fraud",IF(O14="Yes","Unresolved - RNS with contract",IF(N14="Yes","Legitimate (provisional)","Unresolved - partial docs"))) -> Legitimate (provisional) | T14: =INDEX('Transaction Evidence'!$F$2:$F$38,MATCH($A14,'Transaction Evidence'!$A$2:$A$38,0)) -> Contract/PO/SPK, invoice, work/hand-over report, evidence of receipt of goods/services, and Board of Directors approval are on file for this transaction.
A15: ='Outgoing Transactions'!B12 -> ESM-OUT-011 | B15: =DATEVALUE('Outgoing Transactions'!C12) -> 45188 | C15: ='Outgoing Transactions'!D12 -> ESM-BX-01 | D15: ='Outgoing Transactions'!F12 -> PT Laut Arafura Media | E15: ='Outgoing Transactions'!G12 -> VND-MD-02 | F15: ='Outgoing Transactions'!H12 -> Bank Cakra | G15: =INDEX('Transaction Evidence'!$B$2:$B$38,MATCH($A15,'Transaction Evidence'!$A$2:$A$38,0)) -> REQ-MKT-0919 | H15: =INDEX('Transaction Evidence'!$D$2:$D$38,MATCH($A15,'Transaction Evidence'!$A$2:$A$38,0)) -> 350000000 | I15: =INDEX('Payment Approval'!$E$2:$E$38,MATCH($G15,'Payment Approval'!$B$2:$B$38,0)) -> Media and promotional services | J15: =INDEX('Payment Approval'!$F$2:$F$38,MATCH($G15,'Payment Approval'!$B$2:$B$38,0)) -> USR-FIN-02 | K15: =INDEX('Payment Approval'!$G$2:$G$38,MATCH($G15,'Payment Approval'!$B$2:$B$38,0)) -> USR-FIN-02 | L15: =INDEX('Payment Approval'!$H$2:$H$38,MATCH($G15,'Payment Approval'!$B$2:$B$38,0)) -> USR-FIN-02 | M15: =IF(H15=INDEX('Payment Approval'!$C$2:$C$38,MATCH($G15,'Payment Approval'!$B$2:$B$38,0)),"OK","DIFF") -> OK | N15: =IF(ISNUMBER(SEARCH("Contract/PO/SPK; Invoice; Work",INDEX('Transaction Evidence'!$E$2:$E$38,MATCH($A15,'Transaction Evidence'!$A$2:$A$38,0)))),"Yes","No") -> No | O15: =IF(D15="PT Rinjani Niaga Sentosa","Yes","No") -> No | P15: =IF(AND(J15=K15,K15=L15),"Yes","No") -> Yes | Q15: =IF(H15>=$W$1,"Yes","No") -> No | R15: =IF(COUNTIF('Ref - Booklet Data'!$C$14:$C$19,E15)>0,"Registered","Not in extract") -> Not in extract | S15: =IF(AND(O15="Yes",N15="No"),"Suspected fraud",IF(O15="Yes","Unresolved - RNS with contract",IF(N15="Yes","Legitimate (provisional)","Unresolved - partial docs"))) -> Unresolved - partial docs | T15: =INDEX('Transaction Evidence'!$F$2:$F$38,MATCH($A15,'Transaction Evidence'!$A$2:$A$38,0)) -> An invoice and promotional materials are on file for this transaction. No PO/SPK or complete evidence of deliverables was located.
A16: ='Outgoing Transactions'!B13 -> ESM-OUT-012 | B16: =DATEVALUE('Outgoing Transactions'!C13) -> 45196 | C16: ='Outgoing Transactions'!D13 -> ESM-BY-01 | D16: ='Outgoing Transactions'!F13 -> PT Rinjani Niaga Sentosa | E16: ='Outgoing Transactions'!G13 -> RNS-BR-01 | F16: ='Outgoing Transactions'!H13 -> Bank Rinjani | G16: =INDEX('Transaction Evidence'!$B$2:$B$38,MATCH($A16,'Transaction Evidence'!$A$2:$A$38,0)) -> REQ-RNS-013 | H16: =INDEX('Transaction Evidence'!$D$2:$D$38,MATCH($A16,'Transaction Evidence'!$A$2:$A$38,0)) -> 550000000 | I16: =INDEX('Payment Approval'!$E$2:$E$38,MATCH($G16,'Payment Approval'!$B$2:$B$38,0)) -> Operational activity settlement | J16: =INDEX('Payment Approval'!$F$2:$F$38,MATCH($G16,'Payment Approval'!$B$2:$B$38,0)) -> USR-FIN-02 | K16: =INDEX('Payment Approval'!$G$2:$G$38,MATCH($G16,'Payment Approval'!$B$2:$B$38,0)) -> USR-FIN-02 | L16: =INDEX('Payment Approval'!$H$2:$H$38,MATCH($G16,'Payment Approval'!$B$2:$B$38,0)) -> USR-FIN-02 | M16: =IF(H16=INDEX('Payment Approval'!$C$2:$C$38,MATCH($G16,'Payment Approval'!$B$2:$B$38,0)),"OK","DIFF") -> OK | N16: =IF(ISNUMBER(SEARCH("Contract/PO/SPK; Invoice; Work",INDEX('Transaction Evidence'!$E$2:$E$38,MATCH($A16,'Transaction Evidence'!$A$2:$A$38,0)))),"Yes","No") -> No | O16: =IF(D16="PT Rinjani Niaga Sentosa","Yes","No") -> Yes | P16: =IF(AND(J16=K16,K16=L16),"Yes","No") -> Yes | Q16: =IF(H16>=$W$1,"Yes","No") -> No | R16: =IF(COUNTIF('Ref - Booklet Data'!$C$14:$C$19,E16)>0,"Registered","Not in extract") -> Registered | S16: =IF(AND(O16="Yes",N16="No"),"Suspected fraud",IF(O16="Yes","Unresolved - RNS with contract",IF(N16="Yes","Legitimate (provisional)","Unresolved - partial docs"))) -> Suspected fraud | T16: =INDEX('Transaction Evidence'!$F$2:$F$38,MATCH($A16,'Transaction Evidence'!$A$2:$A$38,0)) -> Only a Payment Request, transfer evidence, and email/internal instructions are on file for this transaction. No contract, PO/SPK, work/delivery report, or evidence of
... A41: ='Outgoing Transactions'!B38 -> ESM-OUT-037 | B41: =DATEVALUE('Outgoing Transactions'!C38) -> 45621 | C41: ='Outgoing Transactions'!D38 -> ESM-BX-01 | D41: ='Outgoing Transactions'!F38 -> PT Laut Timor Properti | E41: ='Outgoing Transactions'!G38 -> VND-TP-01 | F41: ='Outgoing Transactions'!H38 -> Bank Cakra | G41: =INDEX('Transaction Evidence'!$B$2:$B$38,MATCH($A41,'Transaction Evidence'!$A$2:$A$38,0)) -> INV-LT-1125 | H41: =INDEX('Transaction Evidence'!$D$2:$D$38,MATCH($A41,'Transaction Evidence'!$A$2:$A$38,0)) -> 520000000 | I41: =INDEX('Payment Approval'!$E$2:$E$38,MATCH($G41,'Payment Approval'!$B$2:$B$38,0)) -> Location maintenance services | J41: =INDEX('Payment Approval'!$F$2:$F$38,MATCH($G41,'Payment Approval'!$B$2:$B$38,0)) -> USR-FIN-02 | K41: =INDEX('Payment Approval'!$G$2:$G$38,MATCH($G41,'Payment Approval'!$B$2:$B$38,0)) -> USR-FIN-02 | L41: =INDEX('Payment Approval'!$H$2:$H$38,MATCH($G41,'Payment Approval'!$B$2:$B$38,0)) -> USR-FIN-02 | M41: =IF(H41=INDEX('Payment Approval'!$C$2:$C$38,MATCH($G41,'Payment Approval'!$B$2:$B$38,0)),"OK","DIFF") -> OK | N41: =IF(ISNUMBER(SEARCH("Contract/PO/SPK; Invoice; Work",INDEX('Transaction Evidence'!$E$2:$E$38,MATCH($A41,'Transaction Evidence'!$A$2:$A$38,0)))),"Yes","No") -> No | O41: =IF(D41="PT Rinjani Niaga Sentosa","Yes","No") -> No | P41: =IF(AND(J41=K41,K41=L41),"Yes","No") -> Yes | Q41: =IF(H41>=$W$1,"Yes","No") -> No | R41: =IF(COUNTIF('Ref - Booklet Data'!$C$14:$C$19,E41)>0,"Registered","Not in extract") -> Not in extract | S41: =IF(AND(O41="Yes",N41="No"),"Suspected fraud",IF(O41="Yes","Unresolved - RNS with contract",IF(N41="Yes","Legitimate (provisional)","Unresolved - partial docs"))) -> Unresolved - partial docs | T41: =INDEX('Transaction Evidence'!$F$2:$F$38,MATCH($A41,'Transaction Evidence'!$A$2:$A$38,0)) -> An invoice and location photos are on file for this transaction. No contract or work report was located.
A42: TOTAL | H42: =SUM(H5:H41) -> 20080000000

Sheet D-Fund Tracing
A1: D. Fund tracing: ESM account to beneficiary (Q4)
A2: All figures are SUMIFS/COUNTIFS on C-Outgoing Analysis.
A4: Beneficiary | B4: # Payments | C4: Total (IDR) | D4: % of Outgoing | E4: # Distinct Bene Accounts | F4: # Payments w/ full docs | G4: # Payments not in change-log | H4: Total paid without full docs
A5: PT Rinjani Niaga Sentosa | B5: =COUNTIF('C-Outgoing Analysis'!$D$5:$D$41,A5) -> 16 | C5: =SUMIFS('C-Outgoing Analysis'!$H$5:$H$41,'C-Outgoing Analysis'!$D$5:$D$41,A5) -> 13500000000 | D5: =C5/$C$15 -> 0.67231076 | E5: =SUMPRODUCT(('C-Outgoing Analysis'!$D$5:$D$41=A5)/COUNTIFS('C-Outgoing Analysis'!$D$5:$D$41,'C-Outgoing Analysis'!$D$5:$D$41,'C-Outgoing Analysis'!$E$5:$E$41,'C-Outgoing Analysis'!$E$5:$E$41)) -> 1 | F5: =COUNTIFS('C-Outgoing Analysis'!$D$5:$D$41,A5,'C-Outgoing Analysis'!$N$5:$N$41,"Yes") -> 1 | G5: =COUNTIFS('C-Outgoing Analysis'!$D$5:$D$41,A5,'C-Outgoing Analysis'!$R$5:$R$41,"Not in extract") -> 0 | H5: =SUMIFS('C-Outgoing Analysis'!$H$5:$H$41,'C-Outgoing Analysis'!$D$5:$D$41,A5,'C-Outgoing Analysis'!$N$5:$N$41,"No") -> 13000000000
A6: PT Laut Banda Pangan | B6: =COUNTIF('C-Outgoing Analysis'!$D$5:$D$41,A6) -> 4 | C6: =SUMIFS('C-Outgoing Analysis'!$H$5:$H$41,'C-Outgoing Analysis'!$D$5:$D$41,A6) -> 1150000000 | D6: =C6/$C$15 -> 0.057270916 | E6: =SUMPRODUCT(('C-Outgoing Analysis'!$D$5:$D$41=A6)/COUNTIFS('C-Outgoing Analysis'!$D$5:$D$41,'C-Outgoing Analysis'!$D$5:$D$41,'C-Outgoing Analysis'!$E$5:$E$41,'C-Outgoing Analysis'!$E$5:$E$41)) -> 4 | F6: =COUNTIFS('C-Outgoing Analysis'!$D$5:$D$41,A6,'C-Outgoing Analysis'!$N$5:$N$41,"Yes") -> 2 | G6: =COUNTIFS('C-Outgoing Analysis'!$D$5:$D$41,A6,'C-Outgoing Analysis'!$R$5:$R$41,"Not in extract") -> 3 | H6: =SUMIFS('C-Outgoing Analysis'!$H$5:$H$41,'C-Outgoing Analysis'!$D$5:$D$41,A6,'C-Outgoing Analysis'!$N$5:$N$41,"No") -> 600000000
A7: PT Laut Sawu Distribusi | B7: =COUNTIF('C-Outgoing Analysis'!$D$5:$D$41,A7) -> 3 | C7: =SUMIFS('C-Outgoing Analysis'!$H$5:$H$41,'C-Outgoing Analysis'!$D$5:$D$41,A7) -> 900000000 | D7: =C7/$C$15 -> 0.044820717 | E7: =SUMPRODUCT(('C-Outgoing Analysis'!$D$5:$D$41=A7)/COUNTIFS('C-Outgoing Analysis'!$D$5:$D$41,'C-Outgoing Analysis'!$D$5:$D$41,'C-Outgoing Analysis'!$E$5:$E$41,'C-Outgoing Analysis'!$E$5:$E$41)) -> 3 | F7: =COUNTIFS('C-Outgoing Analysis'!$D$5:$D$41,A7,'C-Outgoing Analysis'!$N$5:$N$41,"Yes") -> 1 | G7: =COUNTIFS('C-Outgoing Analysis'!$D$5:$D$41,A7,'C-Outgoing Analysis'!$R$5:$R$41,"Not in extract") -> 3 | H7: =SUMIFS('C-Outgoing Analysis'!$H$5:$H$41,'C-Outgoing Analysis'!$D$5:$D$41,A7,'C-Outgoing Analysis'!$N$5:$N$41,"No") -> 750000000
A8: PT Laut Maluku Proyek | B8: =COUNTIF('C-Outgoing Analysis'!$D$5:$D$41,A8) -> 2 | C8: =SUMIFS('C-Outgoing Analysis'!$H$5:$H$41,'C-Outgoing Analysis'!$D$5:$D$41,A8) -> 760000000 | D8: =C8/$C$15 -> 0.037848606 | E8: =SUMPRODUCT(('C-Outgoing Analysis'!$D$5:$D$41=A8)/COUNTIFS('C-Outgoing Analysis'!$D$5:$D$41,'C-Outgoing Analysis'!$D$5:$D$41,'C-Outgoing Analysis'!$E$5:$E$41,'C-Outgoing Analysis'!$E$5:$E$41)) -> 2 | F8: =COUNTIFS('C-Outgoing Analysis'!$D$5:$D$41,A8,'C-Outgoing Analysis'!$N$5:$N$41,"Yes") -> 0 | G8: =COUNTIFS('C-Outgoing Analysis'!$D$5:$D$41,A8,'C-Outgoing Analysis'!$R$5:$R$41,"Not in extract") -> 1 | H8: =SUMIFS('C-Outgoing Analysis'!$H$5:$H$41,'C-Outgoing Analysis'!$D$5:$D$41,A8,'C-Outgoing Analysis'!$N$5:$N$41,"No") -> 760000000
A9: PT Laut Jawa Tomasan | B9: =COUNTIF('C-Outgoing Analysis'!$D$5:$D$41,A9) -> 2 | C9: =SUMIFS('C-Outgoing Analysis'!$H$5:$H$41,'C-Outgoing Analysis'!$D$5:$D$41,A9) -> 750000000 | D9: =C9/$C$15 -> 0.037350598 | E9: =SUMPRODUCT(('C-Outgoing Analysis'!$D$5:$D$41=A9)/COUNTIFS('C-Outgoing Analysis'!$D$5:$D$41,'C-Outgoing Analysis'!$D$5:$D$41,'C-Outgoing Analysis'!$E$5:$E$41,'C-Outgoing Analysis'!$E$5:$E$41)) -> 2 | F9: =COUNTIFS('C-Outgoing Analysis'!$D$5:$D$41,A9,'C-Outgoing Analysis'!$N$5:$N$41,"Yes") -> 1 | G9: =COUNTIFS('C-Outgoing Analysis'!$D$5:$D$41,A9,'C-Outgoing Analysis'!$R$5:$R$41,"Not in extract") -> 1 | H9: =SUMIFS('C-Outgoing Analysis'!$H$5:$H$41,'C-Outgoing Analysis'!$D$5:$D$41,A9,'C-Outgoing Analysis'!$N$5:$N$41,"No") -> 450000000
A10: PT Laut Timor Properti | B10: =COUNTIF('C-Outgoing Analysis'!$D$5:$D$41,A10) -> 2 | C10: =SUMIFS('C-Outgoing Analysis'!$H$5:$H$41,'C-Outgoing Analysis'!$D$5:$D$41,A10) -> 720000000 | D10: =C10/$C$15 -> 0.035856574 | E10: =SUMPRODUCT(('C-Outgoing Analysis'!$D$5:$D$41=A10)/COUNTIFS('C-Outgoing Analysis'!$D$5:$D$41,'C-Outgoing Analysis'!$D$5:$D$41,'C-Outgoing Analysis'!$E$5:$E$41,'C-Outgoing Analysis'!$E$5:$E$41)) -> 2 | F10: =COUNTIFS('C-Outgoing Analysis'!$D$5:$D$41,A10,'C-Outgoing Analysis'!$N$5:$N$41,"Yes") -> 1 | G10: =COUNTIFS('C-Outgoing Analysis'!$D$5:$D$41,A10,'C-Outgoing Analysis'!$R$5:$R$41,"Not in extract") -> 2 | H10: =SUMIFS('C-Outgoing Analysis'!$H$5:$H$41,'C-Outgoing Analysis'!$D$5:$D$41,A10,'C-Outgoing Analysis'!$N$5:$N$41,"No") -> 520000000
A11: PT Laut Arafura Media | B11: =COUNTIF('C-Outgoing Analysis'!$D$5:$D$41,A11) -> 2 | C11: =SUMIFS('C-Outgoing Analysis'!$H$5:$H$41,'C-Outgoing Analysis'!$D$5:$D$41,A11) -> 650000000 | D11: =C11/$C$15 -> 0.032370518 | E11: =SUMPRODUCT(('C-Outgoing Analysis'!$D$5:$D$41=A11)/COUNTIFS('C-Outgoing Analysis'!$D$5:$D$41,'C-Outgoing Analysis'!$D$5:$D$41,'C-Outgoing Analysis'!$E$5:$E$41,'C-Outgoing Analysis'!$E$5:$E$41)) -> 2 | F11: =COUNTIFS('C-Outgoing Analysis'!$D$5:$D$41,A11,'C-Outgoing Analysis'!$N$5:$N$41,"Yes") -> 1 | G11: =COUNTIFS('C-Outgoing Analysis'!$D$5:$D$41,A11,'C-Outgoing Analysis'!$R$5:$R$41,"Not in extract") -> 2 | H11: =SUMIFS('C-Outgoing Analysis'!$H$5:$H$41,'C-Outgoing Analysis'!$D$5:$D$41,A11,'C-Outgoing Analysis'!$N$5:$N$41,"No") -> 350000000
A12: PT Laut Seram Konsultan | B12: =COUNTIF('C-Outgoing Analysis'!$D$5:$D$41,A12) -> 2 | C12: =SUMIFS('C-Outgoing Analysis'!$H$5:$H$41,'C-Outgoing Analysis'!$D$5:$D$41,A12) -> 650000000 | D12: =C12/$C$15 -> 0.032370518 | E12: =SUMPRODUCT(('C-Outgoing Analysis'!$D$5:$D$41=A12)/COUNTIFS('C-Outgoing Analysis'!$D$5:$D$41,'C-Outgoing Analysis'!$D$5:$D$41,'C-Outgoing Analysis'!$E$5:$E$41,'C-Outgoing Analysis'!$E$5:$E$41)) -> 2 | F12: =COUNTIFS('C-Outgoing Analysis'!$D$5:$D$41,A12,'C-Outgoing Analysis'!$N$5:$N$41,"Yes") -> 1 | G12: =COUNTIFS('C-Outgoing Analysis'!$D$5:$D$41,A12,'C-Outgoing Analysis'!$R$5:$R$41,"Not in extract") -> 2 | H12: =SUMIFS('C-Outgoing Analysis'!$H$5:$H$41,'C-Outgoing Analysis'!$D$5:$D$41,A12,'C-Outgoing Analysis'!$N$5:$N$41,"No") -> 450000000
A13: PT Laut Natuna Jasa | B13: =COUNTIF('C-Outgoing Analysis'!$D$5:$D$41,A13) -> 2 | C13: =SUMIFS('C-Outgoing Analysis'!$H$5:$H$41,'C-Outgoing Analysis'!$D$5:$D$41,A13) -> 470000000 | D13: =C13/$C$15 -> 0.023406375 | E13: =SUMPRODUCT(('C-Outgoing Analysis'!$D$5:$D$41=A13)/COUNTIFS('C-Outgoing Analysis'!$D$5:$D$41,'C-Outgoing Analysis'!$D$5:$D$41,'C-Outgoing Analysis'!$E$5:$E$41,'C-Outgoing Analysis'!$E$5:$E$41)) -> 2 | F13: =COUNTIFS('C-Outgoing Analysis'!$D$5:$D$41,A13,'C-Outgoing Analysis'!$N$5:$N$41,"Yes") -> 1 | G13: =COUNTIFS('C-Outgoing Analysis'!$D$5:$D$41,A13,'C-Outgoing Analysis'!$R$5:$R$41,"Not in extract") -> 2 | H13: =SUMIFS('C-Outgoing Analysis'!$H$5:$H$41,'C-Outgoing Analysis'!$D$5:$D$41,A13,'C-Outgoing Analysis'!$N$5:$N$41,"No") -> 420000000
A14: PT Laut Flores Teknologi | B14: =COUNTIF('C-Outgoing Analysis'!$D$5:$D$41,A14) -> 2 | C14: =SUMIFS('C-Outgoing Analysis'!$H$5:$H$41,'C-Outgoing Analysis'!$D$5:$D$41,A14) -> 530000000 | D14: =C14/$C$15 -> 0.026394422 | E14: =SUMPRODUCT(('C-Outgoing Analysis'!$D$5:$D$41=A14)/COUNTIFS('C-Outgoing Analysis'!$D$5:$D$41,'C-Outgoing Analysis'!$D$5:$D$41,'C-Outgoing Analysis'!$E$5:$E$41,'C-Outgoing Analysis'!$E$5:$E$41)) -> 2 | F14: =COUNTIFS('C-Outgoing Analysis'!$D$5:$D$41,A14,'C-Outgoing Analysis'!$N$5:$N$41,"Yes") -> 1 | G14: =COUNTIFS('C-Outgoing Analysis'!$D$5:$D$41,A14,'C-Outgoing Analysis'!$R$5:$R$41,"Not in extract") -> 1 | H14: =SUMIFS('C-Outgoing Analysis'!$H$5:$H$41,'C-Outgoing Analysis'!$D$5:$D$41,A14,'C-Outgoing Analysis'!$N$5:$N$41,"No") -> 280000000
A15: TOTAL | B15: =SUM(B5:B14) -> 37 | C15: =SUM(C5:C14) -> 20080000000 | E15: =SUM(E5:E14) -> 22 | F15: =SUM(F5:F14) -> 10 | G15: =SUM(G5:G14) -> 17 | H15: =SUM(H5:H14) -> 17580000000
A18: By ESM bank account
A19: ESM Account | B19: Receipts (IDR) | C19: Payments to all (IDR) | D19: Payments to RNS (IDR) | E19: RNS % of account payments
A20: ESM-BX-01 | B20: =SUMIFS('Incoming Transactions'!$J$2:$J$41,'Incoming Transactions'!$D$2:$D$41,A20) -> 13580000000 | C20: =SUMIFS('C-Outgoing Analysis'!$H$5:$H$41,'C-Outgoing Analysis'!$C$5:$C$41,A20) -> 10245000000 | D20: =SUMIFS('C-Outgoing Analysis'!$H$5:$H$41,'C-Outgoing Analysis'!$C$5:$C$41,A20,'C-Outgoing Analysis'!$O$5:$O$41,"Yes") -> 5425000000 | E20: =D20/C20 -> 0.5295266
A21: ESM-BY-01 | B21: =SUMIFS('Incoming Transactions'!$J$2:$J$41,'Incoming Transactions'!$D$2:$D$41,A21) -> 13350000000 | C21: =SUMIFS('C-Outgoing Analysis'!$H$5:$H$41,'C-Outgoing Analysis'!$C$5:$C$41,A21) -> 9835000000 | D21: =SUMIFS('C-Outgoing Analysis'!$H$5:$H$41,'C-Outgoing Analysis'!$C$5:$C$41,A21,'C-Outgoing Analysis'!$O$5:$O$41,"Yes") -> 8075000000 | E21: =D21/C21 -> 0.82104728
A22: TOTAL | B22: =SUM(B20:B21) -> 26930000000 | C22: =SUM(C20:C21) -> 20080000000 | D22: =SUM(D20:D21) -> 13500000000 | E22: =D22/C22 -> 0.67231076
A25: RNS payment stream (chronological order of Outgoing sheet)
A26: Txn ID | B26: Date | C26: ESM Account | D26: Reference | E26: Amount (IDR) | F26: Cumulative RNS (IDR) | G26: Description
A27: ='C-Outgoing Analysis'!A6 -> ESM-OUT-002 | B27: ='C-Outgoing Analysis'!B6 -> 45034 | C27: ='C-Outgoing Analysis'!C6 -> ESM-BY-01 | D27: ='C-Outgoing Analysis'!G6 -> REQ-RNS-001 | E27: ='C-Outgoing Analysis'!H6 -> 920000000 | F27: =SUM($E$27:E27) -> 920000000 | G27: ='C-Outgoing Analysis'!I6 -> Expansion cost adjustment
A28: ='C-Outgoing Analysis'!A7 -> ESM-OUT-003 | B28: ='C-Outgoing Analysis'!B7 -> 45057 | C28: ='C-Outgoing Analysis'!C7 -> ESM-BX-01 | D28: ='C-Outgoing Analysis'!G7 -> REQ-RNS-015 | E28: ='C-Outgoing Analysis'!H7 -> 975000000 | F28: =SUM($E$27:E28) -> 1895000000 | G28: ='C-Outgoing Analysis'!I7 -> Project fund adjustment
A29: ='C-Outgoing Analysis'!A10 -> ESM-OUT-006 | B29: ='C-Outgoing Analysis'!B10 -> 45106 | C29: ='C-Outgoing Analysis'!C10 -> ESM-BY-01 | D29: ='C-Outgoing Analysis'!G10 -> REQ-RNS-007 | E29: ='C-Outgoing Analysis'!H10 -> 900000000 | F29: =SUM($E$27:E29) -> 2795000000 | G29: ='C-Outgoing Analysis'!I10 -> Expansion needs management
A30: ='C-Outgoing Analysis'!A11 -> ESM-OUT-007 | B30: ='C-Outgoing Analysis'!B11 -> 45119 | C30: ='C-Outgoing Analysis'!C11 -> ESM-BX-01 | D30: ='C-Outgoing Analysis'!G11 -> REQ-RNS-011 | E30: ='C-Outgoing Analysis'!H11 -> 850000000 | F30: =SUM($E$27:E30) -> 3645000000 | G30: ='C-Outgoing Analysis'!I11 -> Expansion cost reimbursement
A31: ='C-Outgoing Analysis'!A13 -> ESM-OUT-009 | B31: ='C-Outgoing Analysis'!B13 -> 45162 | C31: ='C-Outgoing Analysis'!C13 -> ESM-BX-01 | D31: ='C-Outgoing Analysis'!G13 -> REQ-RNS-003 | E31: ='C-Outgoing Analysis'!H13 -> 950000000 | F31: =SUM($E$27:E31) -> 4595000000 | G31: ='C-Outgoing Analysis'!I13 -> Outlet needs payment
A32: ='C-Outgoing Analysis'!A16 -> ESM-OUT-012 | B32: ='C-Outgoing Analysis'!B16 -> 45196 | C32: ='C-Outgoing Analysis'!C16 -> ESM-BY-01 | D32: ='C-Outgoing Analysis'!G16 -> REQ-RNS-013 | E32: ='C-Outgoing Analysis'!H16 -> 550000000 | F32: =SUM($E$27:E32) -> 5145000000 | G32: ='C-Outgoing Analysis'!I16 -> Operational activity settlement
A33: ='C-Outgoing Analysis'!A20 -> ESM-OUT-016 | B33: ='C-Outgoing Analysis'!B20 -> 45246 | C33: ='C-Outgoing Analysis'!C20 -> ESM-BY-01 | D33: ='C-Outgoing Analysis'!G20 -> REQ-RNS-009 | E33: ='C-Outgoing Analysis'!H20 -> 750000000 | F33: =SUM($E$27:E33) -> 5895000000 | G33: ='C-Outgoing Analysis'!I20 -> Payment adjustment
A34: ='C-Outgoing Analysis'!A22 -> ESM-OUT-018 | B34: ='C-Outgoing Analysis'!B22 -> 45271 | C34: ='C-Outgoing Analysis'!C22 -> ESM-BY-01 | D34: ='C-Outgoing Analysis'!G22 -> REQ-RNS-005 | E34: ='C-Outgoing Analysis'!H22 -> 975000000 | F34: =SUM($E$27:E34) -> 6870000000 | G34: ='C-Outgoing Analysis'!I22 -> Expansion fund placement
A35: ='C-Outgoing Analysis'!A24 -> ESM-OUT-020 | B35: ='C-Outgoing Analysis'!B24 -> 45308 | C35: ='C-Outgoing Analysis'!C24 -> ESM-BY-01 | D35: ='C-Outgoing Analysis'!G24 -> REQ-RNS-002 | E35: ='C-Outgoing Analysis'!H24 -> 880000000 | F35: =SUM($E$27:E35) -> 7750000000 | G35: ='C-Outgoing Analysis'!I24 -> Operational cost settlement
A36: ='C-Outgoing Analysis'!A27 -> ESM-OUT-023 | B36: ='C-Outgoing Analysis'!B27 -> 45345 | C36: ='C-Outgoing Analysis'!C27 -> ESM-BX-01 | D36: ='C-Outgoing Analysis'!G27 -> REQ-RNS-008 | E36: ='C-Outgoing Analysis'!H27 -> 850000000 | F36: =SUM($E$27:E36) -> 8600000000 | G36: ='C-Outgoing Analysis'!I27 -> Development cost payment
A37: ='C-Outgoing Analysis'!A28 -> ESM-OUT-024 | B37: ='C-Outgoing Analysis'!B28 -> 45372 | C37: ='C-Outgoing Analysis'!C28 -> ESM-BY-01 | D37: ='C-Outgoing Analysis'!G28 -> REQ-RNS-012 | E37: ='C-Outgoing Analysis'!H28 -> 800000000 | F37: =SUM($E$27:E37) -> 9400000000 | G37: ='C-Outgoing Analysis'!I28 -> Expansion activity payment
A38: ='C-Outgoing Analysis'!A30 -> ESM-OUT-026 | B38: ='C-Outgoing Analysis'!B30 -> 45404 | C38: ='C-Outgoing Analysis'!C30 -> ESM-BY-01 | D38: ='C-Outgoing Analysis'!G30 -> CTR-RNS-2024-01 | E38: ='C-Outgoing Analysis'!H30 -> 500000000 | F38: =SUM($E$27:E38) -> 9900000000 | G38: ='C-Outgoing Analysis'!I30 -> Area expansion coordination services
A39: ='C-Outgoing Analysis'!A31 -> ESM-OUT-027 | B39: ='C-Outgoing Analysis'!B31 -> 45426 | C39: ='C-Outgoing Analysis'!C31 -> ESM-BX-01 | D39: ='C-Outgoing Analysis'!G31 -> REQ-RNS-004 | E39: ='C-Outgoing Analysis'!H31 -> 850000000 | F39: =SUM($E$27:E39) -> 10750000000 | G39: ='C-Outgoing Analysis'!I31 -> Expansion needs management
A40: ='C-Outgoing Analysis'!A34 -> ESM-OUT-030 | B40: ='C-Outgoing Analysis'!B34 -> 45492 | C40: ='C-Outgoing Analysis'!C34 -> ESM-BY-01 | D40: ='C-Outgoing Analysis'!G34 -> REQ-RNS-014 | E40: ='C-Outgoing Analysis'!H34 -> 975000000 | F40: =SUM($E$27:E40) -> 11725000000 | G40: ='C-Outgoing Analysis'!I34 -> Development cost reallocation
A41: ='C-Outgoing Analysis'!A38 -> ESM-OUT-034 | B41: ='C-Outgoing Analysis'!B38 -> 45538 | C41: ='C-Outgoing Analysis'!C38 -> ESM-BY-01 | D41: ='C-Outgoing Analysis'!G38 -> REQ-RNS-006 | E41: ='C-Outgoing Analysis'!H38 -> 825000000 | F41: =SUM($E$27:E41) -> 12550000000 | G41: ='C-Outgoing Analysis'!I38 -> Project fund adjustment
A42: ='C-Outgoing Analysis'!A39 -> ESM-OUT-035 | B42: ='C-Outgoing Analysis'!B39 -> 45573 | C42: ='C-Outgoing Analysis'!C39 -> ESM-BX-01 | D42: ='C-Outgoing Analysis'!G39 -> REQ-RNS-010 | E42: ='C-Outgoing Analysis'!H39 -> 950000000 | F42: =SUM($E$27:E42) -> 13500000000 | G42: ='C-Outgoing Analysis'!I39 -> Operational funds held in custody
A44: Rows picked by position of RNS in C-Outgoing Analysis (rows 6,7,10,...). If the source order changes, re-pick. Check: total below must equal RNS total above.
A45: Check total | E45: =SUM(E27:E42) -> 13500000000 | F45: =IF(E45=C5,"OK - ties to RNS total","MISMATCH") -> OK - ties to RNS total

Sheet H-Classification
A1: H. Population classification (Q7) with mathematical tie-out
A2: Basis: documentation completeness x beneficiary. "Legitimate" is provisional until beneficiary account is confirmed against the full vendor master.
A4: Classification | B4: # Txn | C4: Amount (IDR) | D4: % of Outgoing | E4: Evidentiary basis
A5: Suspected fraud | B5: =COUNTIF('C-Outgoing Analysis'!$S$5:$S$41,A5) -> 15 | C5: =SUMIFS('C-Outgoing Analysis'!$H$5:$H$41,'C-Outgoing Analysis'!$S$5:$S$41,A5) -> 13000000000 | D5: =C5/$C$9 -> 0.64741036 | E5: RNS payments supported only by Payment Request, transfer evidence and internal email; no contract/PO/work report/receipt; generic descriptions; maker=checker=approver; rekening & vendor set up by Finance.
A6: Unresolved - RNS with contract | B6: =COUNTIF('C-Outgoing Analysis'!$S$5:$S$41,A6) -> 1 | C6: =SUMIFS('C-Outgoing Analysis'!$H$5:$H$41,'C-Outgoing Analysis'!$S$5:$S$41,A6) -> 500000000 | D6: =C6/$C$9 -> 0.024900398 | E6: RNS payment with full package (CTR-RNS-2024-01) but same counterparty pattern; substance of "coordination services" and signatories to be tested.
A7: Unresolved - partial docs | B7: =COUNTIF('C-Outgoing Analysis'!$S$5:$S$41,A7) -> 12 | C7: =SUMIFS('C-Outgoing Analysis'!$H$5:$H$41,'C-Outgoing Analysis'!$S$5:$S$41,A7) -> 4580000000 | D7: =C7/$C$9 -> 0.22808765 | E7: Non-RNS vendors with invoice/email only; contract, PO, work report or receipt missing; some to accounts not in change-log extract.
A8: Legitimate (provisional) | B8: =COUNTIF('C-Outgoing Analysis'!$S$5:$S$41,A8) -> 9 | C8: =SUMIFS('C-Outgoing Analysis'!$H$5:$H$41,'C-Outgoing Analysis'!$S$5:$S$41,A8) -> 2000000000 | D8: =C8/$C$9 -> 0.099601594 | E8: Full package: contract/PO/SPK, invoice, work/hand-over report, receipt evidence, Board approval.
A9: TOTAL | B9: =SUM(B5:B8) -> 37 | C9: =SUM(C5:C8) -> 20080000000
A10: Tie-out to Evidence total | C10: =SUM('Transaction Evidence'!D2:D38) -> 20080000000 | D10: =IF(C9=C10,"PASS","FAIL") -> PASS
A12: Authorization statistics
A13: Transactions with maker = checker = approver | C13: =COUNTIF('C-Outgoing Analysis'!P5:P41,"Yes") -> 30
A14: Amount of those transactions | C14: =SUMIFS('C-Outgoing Analysis'!H5:H41,'C-Outgoing Analysis'!P5:P41,"Yes") -> 18730000000
A15: Transactions approved by USR-FIN-02 | C15: =COUNTIF('C-Outgoing Analysis'!L5:L41,"USR-FIN-02") -> 37
A16: RNS payments >= threshold | C16: =COUNTIFS('C-Outgoing Analysis'!O5:O41,"Yes",'C-Outgoing Analysis'!Q5:Q41,"Yes") -> 7
A17: RNS payments where maker=checker=approver | C17: =COUNTIFS('C-Outgoing Analysis'!O5:O41,"Yes",'C-Outgoing Analysis'!P5:P41,"Yes") -> 16
A18: Payments to accounts not in change-log extract | C18: =COUNTIF('C-Outgoing Analysis'!R5:R41,"Not in extract") -> 17
A19: Amount to accounts not in extract | C19: =SUMIFS('C-Outgoing Analysis'!H5:H41,'C-Outgoing Analysis'!R5:R41,"Not in extract") -> 5230000000
A20: Evidence vs Approval amount differences | C20: =COUNTIF('C-Outgoing Analysis'!M5:M41,"DIFF") -> 0

Sheet Red Flags
A1: Red flag register (Q1)
A2: Metrics link to the analysis sheets. "Severity": High/Medium indicates priority, not a conclusion of fraud.
A4: # | B4: Area | C4: Red flag | D4: Metric | E4: Source sheet(s) | F4: Severity | G4: Booklet Q
A5: 1 | B5: Disbursement | C5: One counterparty (RNS) receives most outgoing cash | D5: ='D-Fund Tracing'!D5 -> 0.67231076 | E5: D-Fund Tracing | F5: High | G5: Q3,Q4
A6: 2 | B6: Documentation | C6: RNS payments with no contract/PO/work report/receipt (count) | D6: =COUNTIFS('C-Outgoing Analysis'!O5:O41,"Yes",'C-Outgoing Analysis'!N5:N41,"No") -> 15 | E6: C-Outgoing Analysis | F6: High | G6: Q5
A7: 3 | B7: Documentation | C7: RNS payments without full docs (IDR) | D7: =SUMIFS('C-Outgoing Analysis'!H5:H41,'C-Outgoing Analysis'!O5:O41,"Yes",'C-Outgoing Analysis'!N5:N41,"No") -> 13000000000 | E7: C-Outgoing Analysis | F7: High | G7: Q5
A8: 4 | B8: Authorization | C8: Transactions where maker=checker=approver | D8: ='H-Classification'!C13 -> 30 | E8: H-Classification | F8: High | G8: Q6,Q8
A9: 5 | B9: Authorization | C9: All payments approved by a single user (USR-FIN-02) | D9: ='H-Classification'!C15 -> 37 | E9: H-Classification | F9: High | G9: Q6,Q8
A10: 6 | B10: Authorization | C10: RNS payments at/above threshold, clustered just under 1bn | D10: ='H-Classification'!C16 -> 7 | E10: H-Classification | F10: Medium | G10: Q6
A11: 7 | B11: Documentation | C11: Other vendors: payments without full package | D11: =COUNTIFS('C-Outgoing Analysis'!O5:O41,"No",'C-Outgoing Analysis'!N5:N41,"No") -> 12 | E11: C-Outgoing Analysis | F11: Medium | G11: Q5
A12: 8 | B12: Beneficiary | C12: Payments to accounts not in the change-log extract (count) | D12: ='H-Classification'!C18 -> 17 | E12: H-Classification | F12: Medium | G12: Q4
A13: 9 | B13: Beneficiary | C13: Vendors paid to more than one bank account (of 9 non-RNS) | D13: =COUNTIF('D-Fund Tracing'!E6:E14,">1") -> 9 | E13: D-Fund Tracing | F13: Medium | G13: Q4
A14: 10 | B14: Beneficiary | C14: Name mismatch: data "PT Laut Jawa Tomasan" vs master "PT Laut Jawa Kemasan" | D14: =COUNTIF('C-Outgoing Analysis'!D5:D41,"PT Laut Jawa Tomasan") -> 2 | E14: C-Outgoing Analysis; Ref | F14: Medium | G14: Q4
A15: 11 | B15: Beneficiary | C15: Timor Properti: change log account PROP-001 is never used; VND-TP-01/02 paid | D15: =COUNTIF('C-Outgoing Analysis'!D5:D41,"PT Laut Timor Properti") -> 2 | E15: C-Outgoing Analysis; Ref | F15: Medium | G15: Q4
A16: 12 | B16: Relationship | C16: RNS vendor ID format PTY-RNS (not VND-); onboarded by Finance Admin; bank account prepared by Finance, approved by Finance Head | D16: n/a | E16: Ref - Booklet Data | F16: High | G16: Q6
A17: 13 | B17: Relationship | C17: RNS registered address "Kompleks Arunika Blok R 11" - compare with EV-08 (Uranus profile) - NOT yet verifiable | D17: n/a | E17: Ref - Booklet Data | F17: Unverified | G17: Q6
A18: 14 | B18: Receipt | C18: Receipts recorded BEFORE agreement date | D18: ='B-Receipt Recon'!F48 -> 21 | E18: B-Receipt Recon | F18: Medium | G18: Q2
A19: 15 | B19: Receipt | C19: Receipts later than due date though Register says "Paid in Full" | D19: ='B-Receipt Recon'!F49 -> 16 | E19: B-Receipt Recon | F19: Medium | G19: Q2
A20: 16 | B20: Description | C20: Generic descriptions ("adjustment", "expansion needs management") on RNS requests | D20: =COUNTIFS('C-Outgoing Analysis'!O5:O41,"Yes",'C-Outgoing Analysis'!N5:N41,"No") -> 15 | E20: C-Outgoing Analysis | F20: Medium | G20: Q1

Sheet Conclusion & Recs
A1: Conclusions (Q7), control weaknesses (Q8) and recommendations (Q9)
A3: Type | B3: Item | C3: Detail
A4: Conclusion | B4: Suspected fraud | C4: 15 RNS payments (IDR 13.0bn) lack any commercial support and were self-approved. Pattern is consistent with diversion of funds; individual responsibility is NOT concluded.
A5: Conclusion | B5: Unresolved | C5: 12 non-RNS payments with partial documentation (IDR 4.58bn) and 1 RNS contract payment (IDR 0.5bn); need vendor confirmations, full contract set, and account verification.
A6: Conclusion | B6: Legitimate (provisional) | C6: 9 payments (IDR 2.0bn) with complete package; confirm rekening against full vendor master.
A7: Conclusion | B7: Franchise receipts | C7: All 40 receipts reconcile in amount, account and sender (26.93bn). Date anomalies remain as investigation points.
A8: Conclusion | B8: Related party | C8: UNRESOLVED: indicators exist (single approver, Finance-created vendor/account) but EV-07/EV-08 not reviewed; a single matching data point is insufficient per booklet.
A9: Weakness | B9: Segregation of duties | C9: Same user acts as maker, checker and approver on 30 of 37 payments; one user approves all.
A10: Weakness | B10: Approval without substance | C10: Approval record exists even where no contract, PO or delivery evidence exists.
A11: Weakness | B11: Vendor / bank master | C11: Vendor and bank accounts created by Finance and approved by Finance Head; multiple undocumented accounts per vendor.
A12: Weakness | B12: Monitoring | C12: No reconciliation of receipts to due dates; 'Paid in Full' status ignores timing; no review of concentration to one payee.
A13: Recommendation | B13: Authorization | C13: Enforce system-level maker/checker/approver separation by value bands; block same-user approvals; require dual approval (incl. President Director) above a threshold.
A14: Recommendation | B14: Documentation | C14: 3-way match (contract/PO, receipt, invoice) before release; no payment on Payment Request + email alone.
... A18: Next step | B18: Obtain data | C18: User master & approval matrix; EV-01 to EV-08 documents; full vendor and bank master; bank statements/balances; RNS onward transfers.

Sheet Ref - Booklet Data
A1: Reference data transcribed from the case booklet
A2: Source: CPA Days 2026 booklet, Additional Supporting Data Pack, pages 8-10 (transcribed manually from images; not part of the Excel data pack).
A4: Vendor master extract (p.9)
A5: Vendor ID | B5: Legal Name | C5: Status | D5: Onboarding Date | E5: Registered Activity | F5: Registered Address | G5: Responsible Function
A6: VND-001 | B6: PT Laut Banda Pangan | C6: Active | D6: 15-Mar-2022 | E6: Procurement / food ingredients | F6: Jakarta | G6: Vendor Management
A7: VND-002 | B7: PT Laut Jawa Kemasan | C7: Active | D7: 08-Apr-2022 | E7: Packaging procurement | F7: Bekasi | G7: Vendor Management
A8: PTY-RNS | B8: PT Rinjani Niaga Sentosa | C8: Active | D8: 15-Mar-2022 | E8: Management consulting / general trade | F8: Kompleks Arunika Blok R 11, Jakarta | G8: Finance Administration
A9: VND-003 | B9: PT Laut Flores Teknologi | C9: Active | D9: 10-May-2022 | E9: Technology services | F9: Tangerang | G9: Procurement
A10: VND-006 | B10: PT Laut Timor Properti | C10: Active | D10: 17-Aug-2022 | E10: Property / asset counterparty | F10: Jakarta | G10: Finance Administration
A12: Bank account registration & change log (p.9-10)
A13: Log ID | B13: Beneficiary | C13: Registered Account | D13: Bank | E13: Change Type | F13: Effective Date | G13: Prepared By | H13: Reviewed/Approved By Function | I13: Status
A14: BA-001 | B14: PT Laut Banda Pangan | C14: VND-BD-01 | D14: Bank Samudra | E14: Initial registration | F14: 18-Mar-2022 | G14: Vendor Management | H14: Finance Review | I14: Completed
A15: BA-002 | B15: PT Laut Jawa Kemasan | C15: VND-KM-01 | D15: Bank Samudra | E15: Initial registration | F15: 08-Apr-2022 | G15: Vendor Management | H15: Finance Review | I15: Completed
A16: BA-003 | B16: PT Rinjani Niaga Sentosa | C16: RNS-BR-01 | D16: Bank Rinjani | E16: Initial registration | F16: 21-Mar-2022 | G16: Finance | H16: Finance Head | I16: Completed
A17: BA-004 | B17: PT Laut Timor Properti | C17: PROP-001 | D17: Bank Cakra | E17: Initial registration | F17: 17-Aug-2022 | G17: Procurement | H17: Finance Head | I17: Completed
A18: BA-005 | B18: PT Laut Flores Teknologi | C18: VND-TI-01 | D18: Bank Nusantara | E18: Account detail update | F18: 04-Jan-2024 | G18: Finance | H18: Finance Head | I18: Completed
A19: BA-006 | B19: PT Laut Maluku Proyek | C19: VND-PJ-01 | D19: Bank Cakra | E19: Initial registration | F19: 11-Feb-2023 | G19: Procurement | H19: Finance Review | I19: Completed
A21: Note: both tables are extracts, not the complete master. Absence of an account/vendor here is an investigation point, not proof of wrongdoing. Blue = hardcoded input transcribed from booklet.

Sheet Franchise Register
A1: No | B1: Reference | C1: Agreement ID | D1: Partner Name | E1: Outlet Location | F1: Outlet Type | G1: Agreement Date | H1: Franchise Fee Amount | I1: Official ESM Receiving Account | J1: Contract Status | K1: Due Date | L1: Payment Status
A2: 1 | B2: FR-001 | C2: AGR-001 | D2: Partner 01 | E2: Jakarta | F2: Regular Outlet | G2: 03-Jan-2023 | H2: 650000000 | I2: ESM-BX-01 | J2: Active | K2: 02-Feb-2023 | L2: Paid in Full
A3: 2 | B3: FR-002 | C3: AGR-002 | D3: Partner 02 | E3: Bandung | F3: Express Outlet | G3: 06-Feb-2023 | H3: 720000000 | I3: ESM-BY-01 | J3: Active | K3: 08-Mar-2023 | L3: Paid in Full
A4: 3 | B4: FR-003 | C4: AGR-003 | D4: Partner 03 | E4: Surabaya | F4: Premium Outlet | G4: 09-Mar-2023 | H4: 540000000 | I4: ESM-BX-01 | J4: Active | K4: 08-Apr-2023 | L4: Paid in Full
A5: 4 | B5: FR-004 | C5: AGR-004 | D5: Partner 04 | E5: Yogyakarta | F5: Regular Outlet | G5: 12-Apr-2023 | H5: 800000000 | I5: ESM-BY-01 | J5: Active | K5: 12-May-2023 | L5: Paid in Full
A6: 5 | B6: FR-005 | C6: AGR-005 | D6: Partner 05 | E6: Medan | F6: Express Outlet | G6: 15-May-2023 | H6: 610000000 | I6: ESM-BX-01 | J6: Active | K6: 14-Jun-2023 | L6: Paid in Full
A7: 6 | B7: FR-006 | C7: AGR-006 | D7: Partner 06 | E7: Jakarta | F7: Premium Outlet | G7: 18-Jun-2023 | H7: 700000000 | I7: ESM-BY-01 | J7: Active | K7: 18-Jul-2023 | L7: Paid in Full
A8: 7 | B8: FR-007 | C8: AGR-007 | D8: Partner 07 | E8: Bandung | F8: Regular Outlet | G8: 21-Jul-2023 | H8: 560000000 | I8: ESM-BX-01 | J8: Active | K8: 20-Aug-2023 | L8: Paid in Full
A9: 8 | B9: FR-008 | C9: AGR-008 | D9: Partner 08 | E9: Surabaya | F9: Express Outlet | G9: 24-Aug-2023 | H9: 750000000 | I9: ESM-BY-01 | J9: Active | K9: 23-Sep-2023 | L9: Paid in Full
A10: 9 | B10: FR-009 | C10: AGR-009 | D10: Partner 09 | E10: Yogyakarta | F10: Premium Outlet | G10: 02-Sep-2023 | H10: 630000000 | I10: ESM-BX-01 | J10: Active | K10: 02-Oct-2023 | L10: Paid in Full
A11: 10 | B11: FR-010 | C11: AGR-010 | D11: Partner 10 | E11: Medan | F11: Regular Outlet | G11: 05-Oct-2023 | H11: 890000000 | I11: ESM-BY-01 | J11: Active | K11: 04-Nov-2023 | L11: Paid in Full
A12: 11 | B12: FR-011 | C12: AGR-011 | D12: Partner 11 | E12: Jakarta | F12: Express Outlet | G12: 08-Nov-2023 | H12: 700000000 | I12: ESM-BX-01 | J12: Active | K12: 08-Dec-2023 | L12: Paid in Full
A13: 12 | B13: FR-012 | C13: AGR-012 | D13: Partner 12 | E13: Bandung | F13: Premium Outlet | G13: 11-Dec-2023 | H13: 500000000 | I13: ESM-BY-01 | J13: Active | K13: 10-Jan-2024 | L13: Paid in Full
... A41: 40 | B41: FR-040 | C41: AGR-040 | D41: Partner 40 | E41: Medan | F41: Regular Outlet | G41: 20-Apr-2024 | H41: 720000000 | I41: ESM-BY-01 | J41: Active | K41: 20-May-2024 | L41: Paid in Full
F42: TOTAL | H42: =SUM(H2:H41) -> 26930000000

Sheet Outgoing Transactions
A1: No | B1: Transaction ID | C1: Transaction Date | D1: ESM Account | E1: ESM Bank | F1: Beneficiary Name | G1: Beneficiary Account | H1: Beneficiary Bank
A2: 1 | B2: ESM-OUT-001 | C2: 05-Apr-2023 | D2: ESM-BX-01 | E2: Bank Arunika | F2: PT Laut Banda Pangan | G2: VND-BD-01 | H2: Bank Samudra
A3: 2 | B3: ESM-OUT-002 | C3: 18-Apr-2023 | D3: ESM-BY-01 | E3: Bank Yudhistira | F3: PT Rinjani Niaga Sentosa | G3: RNS-BR-01 | H3: Bank Rinjani
A4: 3 | B4: ESM-OUT-003 | C4: 11-May-2023 | D4: ESM-BX-01 | E4: Bank Arunika | F4: PT Rinjani Niaga Sentosa | G4: RNS-BR-01 | H4: Bank Rinjani
A5: 4 | B5: ESM-OUT-004 | C5: 07-Jun-2023 | D5: ESM-BY-01 | E5: Bank Yudhistira | F5: PT Laut Natuna Jasa | G5: VND-JS-02 | H5: Bank Nusantara
A6: 5 | B6: ESM-OUT-005 | C6: 29-Jun-2023 | D6: ESM-BX-01 | E6: Bank Arunika | F6: PT Laut Seram Konsultan | G6: VND-KS-01 | H6: Bank Cakra
A7: 6 | B7: ESM-OUT-006 | C7: 29-Jun-2023 | D7: ESM-BY-01 | E7: Bank Yudhistira | F7: PT Rinjani Niaga Sentosa | G7: RNS-BR-01 | H7: Bank Rinjani
A8: 7 | B8: ESM-OUT-007 | C8: 12-Jul-2023 | D8: ESM-BX-01 | E8: Bank Arunika | F8: PT Rinjani Niaga Sentosa | G8: RNS-BR-01 | H8: Bank Rinjani
A9: 8 | B9: ESM-OUT-008 | C9: 15-Aug-2023 | D9: ESM-BY-01 | E9: Bank Yudhistira | F9: PT Laut Banda Pangan | G9: VND-BD-03 | H9: Bank Cakra
A10: 9 | B10: ESM-OUT-009 | C10: 24-Aug-2023 | D10: ESM-BX-01 | E10: Bank Arunika | F10: PT Rinjani Niaga Sentosa | G10: RNS-BR-01 | H10: Bank Rinjani
A11: 10 | B11: ESM-OUT-010 | C11: 14-Sep-2023 | D11: ESM-BY-01 | E11: Bank Yudhistira | F11: PT Laut Seram Konsultan | G11: VND-KS-02 | H11: Bank Samudra
A12: 11 | B12: ESM-OUT-011 | C12: 19-Sep-2023 | D12: ESM-BX-01 | E12: Bank Arunika | F12: PT Laut Arafura Media | G12: VND-MD-02 | H12: Bank Cakra
A13: 12 | B13: ESM-OUT-012 | C13: 27-Sep-2023 | D13: ESM-BY-01 | E13: Bank Yudhistira | F13: PT Rinjani Niaga Sentosa | G13: RNS-BR-01 | H13: Bank Rinjani
... A38: 37 | B38: ESM-OUT-037 | C38: 25-Nov-2024 | D38: ESM-BX-01 | E38: Bank Arunika | F38: PT Laut Timor Properti | G38: VND-TP-01 | H38: Bank Cakra

Sheet Payment Approval
A1: No | B1: Reference | C1: Amount | D1: Currency | E1: Description | F1: Maker User ID | G1: Checker User ID | H1: Approver User ID
A2: 1 | B2: CTR-2024-011 | C2: 300000000 | D2: IDR | E2: Raw material procurement | F2: USR-FIN-02 | G2: USR-FIN-02 | H2: USR-FIN-02
A3: 2 | B3: REQ-RNS-001 | C3: 920000000 | D3: IDR | E3: Expansion cost adjustment | F3: USR-FIN-02 | G3: USR-FIN-02 | H3: USR-FIN-02
A4: 3 | B4: REQ-RNS-015 | C4: 975000000 | D4: IDR | E4: Project fund adjustment | F4: USR-FIN-02 | G4: USR-FIN-02 | H4: USR-FIN-02
A5: 4 | B5: CTR-2024-057 | C5: 50000000 | D5: IDR | E5: Operational support | F5: USR-FIN-01 | G5: USR-FIN-02 | H5: USR-FIN-02
A6: 5 | B6: INV-LS-2404A | C6: 450000000 | D6: IDR | E6: Development consulting services | F6: USR-FIN-02 | G6: USR-FIN-02 | H6: USR-FIN-02
A7: 6 | B7: REQ-RNS-007 | C7: 900000000 | D7: IDR | E7: Expansion needs management | F7: USR-FIN-02 | G7: USR-FIN-02 | H7: USR-FIN-02
A8: 7 | B8: REQ-RNS-011 | C8: 850000000 | D8: IDR | E8: Expansion cost reimbursement | F8: USR-FIN-02 | G8: USR-FIN-02 | H8: USR-FIN-02
A9: 8 | B9: REQ-ESM-014A | C9: 300000000 | D9: IDR | E9: Operational outgoing | F9: USR-FIN-02 | G9: USR-FIN-02 | H9: USR-FIN-02
A10: 9 | B10: REQ-RNS-003 | C10: 950000000 | D10: IDR | E10: Outlet needs payment | F10: USR-FIN-02 | G10: USR-FIN-02 | H10: USR-FIN-02
A11: 10 | B11: CTR-2024-046 | C11: 200000000 | D11: IDR | E11: Consulting services | F11: USR-FIN-01 | G11: USR-FIN-02 | H11: USR-FIN-02
A12: 11 | B12: REQ-MKT-0919 | C12: 350000000 | D12: IDR | E12: Media and promotional services | F12: USR-FIN-02 | G12: USR-FIN-02 | H12: USR-FIN-02
A13: 12 | B13: REQ-RNS-013 | C13: 550000000 | D13: IDR | E13: Operational activity settlement | F13: USR-FIN-02 | G13: USR-FIN-02 | H13: USR-FIN-02
... A38: 37 | B38: INV-LT-1125 | C38: 520000000 | D38: IDR | E38: Location maintenance services | F38: USR-FIN-02 | G38: USR-FIN-02 | H38: USR-FIN-02

Sheet Agreement Details
A1: No | B1: Agreement ID | C1: Reference | D1: Partner Name | E1: Agreement Date | F1: Contract Period | G1: Franchise Fee Amount | H1: Official ESM Receiving Account | I1: Payment Terms | J1: Contract Status | K1: Contract Document
A2: 1 | B2: AGR-001 | C2: FR-001 | D2: Partner 01 | E2: 03-Jan-2023 | F2: 5 years | G2: 650000000 | H2: ESM-BX-01 | I2: Paid in accordance with the invoice/agreement terms | J2: Active | K2: AGR-001.pdf
A3: 2 | B3: AGR-002 | C3: FR-002 | D3: Partner 02 | E3: 06-Feb-2023 | F3: 5 years | G3: 720000000 | H3: ESM-BY-01 | I3: Paid in accordance with the invoice/agreement terms | J3: Active | K3: AGR-002.pdf
A4: 3 | B4: AGR-003 | C4: FR-003 | D4: Partner 03 | E4: 09-Mar-2023 | F4: 5 years | G4: 540000000 | H4: ESM-BX-01 | I4: Paid in accordance with the invoice/agreement terms | J4: Active | K4: AGR-003.pdf
A5: 4 | B5: AGR-004 | C5: FR-004 | D5: Partner 04 | E5: 12-Apr-2023 | F5: 5 years | G5: 800000000 | H5: ESM-BY-01 | I5: Paid in accordance with the invoice/agreement terms | J5: Active | K5: AGR-004.pdf
A6: 5 | B6: AGR-005 | C6: FR-005 | D6: Partner 05 | E6: 15-May-2023 | F6: 5 years | G6: 610000000 | H6: ESM-BX-01 | I6: Paid in accordance with the invoice/agreement terms | J6: Active | K6: AGR-005.pdf
A7: 6 | B7: AGR-006 | C7: FR-006 | D7: Partner 06 | E7: 18-Jun-2023 | F7: 5 years | G7: 700000000 | H7: ESM-BY-01 | I7: Paid in accordance with the invoice/agreement terms | J7: Active | K7: AGR-006.pdf
A8: 7 | B8: AGR-007 | C8: FR-007 | D8: Partner 07 | E8: 21-Jul-2023 | F8: 5 years | G8: 560000000 | H8: ESM-BX-01 | I8: Paid in accordance with the invoice/agreement terms | J8: Active | K8: AGR-007.pdf
A9: 8 | B9: AGR-008 | C9: FR-008 | D9: Partner 08 | E9: 24-Aug-2023 | F9: 5 years | G9: 750000000 | H9: ESM-BY-01 | I9: Paid in accordance with the invoice/agreement terms | J9: Active | K9: AGR-008.pdf
A10: 9 | B10: AGR-009 | C10: FR-009 | D10: Partner 09 | E10: 02-Sep-2023 | F10: 5 years | G10: 630000000 | H10: ESM-BX-01 | I10: Paid in accordance with the invoice/agreement terms | J10: Active | K10: AGR-009.pdf
A11: 10 | B11: AGR-010 | C11: FR-010 | D11: Partner 10 | E11: 05-Oct-2023 | F11: 5 years | G11: 890000000 | H11: ESM-BY-01 | I11: Paid in accordance with the invoice/agreement terms | J11: Active | K11: AGR-010.pdf
A12: 11 | B12: AGR-011 | C12: FR-011 | D12: Partner 11 | E12: 08-Nov-2023 | F12: 5 years | G12: 700000000 | H12: ESM-BX-01 | I12: Paid in accordance with the invoice/agreement terms | J12: Active | K12: AGR-011.pdf
A13: 12 | B13: AGR-012 | C13: FR-012 | D13: Partner 12 | E13: 11-Dec-2023 | F13: 5 years | G13: 500000000 | H13: ESM-BY-01 | I13: Paid in accordance with the invoice/agreement terms | J13: Active | K13: AGR-012.pdf
... A41: 40 | B41: AGR-040 | C41: FR-040 | D41: Partner 40 | E41: 20-Apr-2024 | F41: 5 years | G41: 720000000 | H41: ESM-BY-01 | I41: Paid in accordance with the invoice/agreement terms | J41: Active | K41: AGR-040.pdf

Sheet Transaction Evidence
A1: Transaction ID | B1: Reference | C1: Beneficiary | D1: Amount | E1: Available Documents/Evidence | F1: Substantive Notes
A2: ESM-OUT-001 | B2: CTR-2024-011 | C2: PT Laut Banda Pangan | D2: 300000000 | E2: Contract/PO/SPK; Invoice; Work/hand-over report; Evidence of receipt of goods/services; Board of Directors approval | F2: Contract/PO/SPK, invoice, work/hand-over report, evidence of receipt of goods/services, and Board of Directors approval are on file for this transaction.
A3: ESM-OUT-002 | B3: REQ-RNS-001 | C3: PT Rinjani Niaga Sentosa | D3: 920000000 | E3: Payment Request; transfer evidence; email/internal instructions | F3: Only a Payment Request, transfer evidence, and email/internal instructions are on file for this transaction. No contract, PO/SPK, work/delivery report, or evidence of
A4: ESM-OUT-003 | B4: REQ-RNS-015 | C4: PT Rinjani Niaga Sentosa | D4: 975000000 | E4: Payment Request; transfer evidence; email/internal instructions | F4: Only a Payment Request, transfer evidence, and email/internal instructions are on file for this transaction. No contract, PO/SPK, work/delivery report, or evidence of
A5: ESM-OUT-004 | B5: CTR-2024-057 | C5: PT Laut Natuna Jasa | D5: 50000000 | E5: Contract/PO/SPK; Invoice; Work/hand-over report; Evidence of receipt of goods/services; Board of Directors | F5: Contract/PO/SPK, invoice, work/hand-over report, evidence of receipt of goods/services, and Board of Directors approval are on file for this transaction.
A6: ESM-OUT-005 | B6: INV-LS-2404A | C6: PT Laut Seram Konsultan | D6: 450000000 | E6: Invoice only; contract/SPK, work report, and evidence of receipt of services are not available. | F6: Only an invoice is on file for this transaction. No contract/SPK, work report, or evidence of receipt of services was located.
A7: ESM-OUT-006 | B7: REQ-RNS-007 | C7: PT Rinjani Niaga Sentosa | D7: 900000000 | E7: Payment Request; transfer evidence; email/internal instructions | F7: Only a Payment Request, transfer evidence, and email/internal instructions are on file for this transaction. No contract, PO/SPK, work/delivery report, or evidence of
A8: ESM-OUT-007 | B8: REQ-RNS-011 | C8: PT Rinjani Niaga Sentosa | D8: 850000000 | E8: Payment Request; transfer evidence; email/internal instructions | F8: Only a Payment Request, transfer evidence, and email/internal instructions are on file for this transaction. No contract, PO/SPK, work/delivery report, or evidence of
A9: ESM-OUT-008 | B9: REQ-ESM-014A | C9: PT Laut Banda Pangan | D9: 300000000 | E9: Payment request and email instruction; invoice and evidence of receipt of benefits are not available. | F9: Only a payment request and email instruction are on file for this transaction. No invoice or evidence of receipt of benefits was located.
A10: ESM-OUT-009 | B10: REQ-RNS-003 | C10: PT Rinjani Niaga Sentosa | D10: 950000000 | E10: Payment Request; transfer evidence; email/internal instructions | F10: Only a Payment Request, transfer evidence, and email/internal instructions are on file for this transaction. No contract, PO/SPK, work/delivery report, or evidence of
A11: ESM-OUT-010 | B11: CTR-2024-046 | C11: PT Laut Seram Konsultan | D11: 200000000 | E11: Contract/PO/SPK; Invoice; Work/hand-over report; Evidence of receipt of goods/services; Board of Directors | F11: Contract/PO/SPK, invoice, work/hand-over report, evidence of receipt of goods/services, and Board of Directors approval are on file for this transaction.
A12: ESM-OUT-011 | B12: REQ-MKT-0919 | C12: PT Laut Arafura Media | D12: 350000000 | E12: Invoice and promotional materials; PO/SPK and complete evidence of deliverables are not available. | F12: An invoice and promotional materials are on file for this transaction. No PO/SPK or complete evidence of deliverables was located.
A13: ESM-OUT-012 | B13: REQ-RNS-013 | C13: PT Rinjani Niaga Sentosa | D13: 550000000 | E13: Payment Request; transfer evidence; email/internal instructions | F13: Only a Payment Request, transfer evidence, and email/internal instructions are on file for this transaction. No contract, PO/SPK, work/delivery report, or evidence of
... A38: ESM-OUT-037 | B38: INV-LT-1125 | C38: PT Laut Timor Properti | D38: 520000000 | E38: Invoice and location photos are available; contract and work report are not available. | F38: An invoice and location photos are on file for this transaction. No contract or work report was located.

Sheet Incoming Transactions
A1: No | B1: Transaction ID | C1: Transaction Date | D1: ESM Account | E1: ESM Bank | F1: Sender Name | G1: Sender Account | H1: Reference | I1: Agreement ID | J1: Amount | K1: Currency | L1: Description | N1: Control | O1: Value
A2: 1 | B2: ESM-IN-001 | C2: 03-Feb-2023 | D2: ESM-BX-01 | E2: Bank Arunika | F2: Partner 01 | G2: MT-01-ACC | H2: FR-001 | I2: AGR-001 | J2: 650000000 | K2: IDR | L2: Franchise fee payment | N2: Total Incoming | O2: =SUM(J2:J41) -> 26930000000
A3: 2 | B3: ESM-IN-002 | C3: 10-Feb-2023 | D3: ESM-BY-01 | E3: Bank Yudhistira | F3: Partner 02 | G3: MT-02-ACC | H3: FR-002 | I3: AGR-002 | J3: 720000000 | K3: IDR | L3: Franchise fee payment
A4: 3 | B4: ESM-IN-003 | C4: 02-Mar-2023 | D4: ESM-BX-01 | E4: Bank Arunika | F4: Partner 03 | G4: MT-03-ACC | H4: FR-003 | I4: AGR-003 | J4: 540000000 | K4: IDR | L4: Franchise fee payment
A5: 4 | B5: ESM-IN-004 | C5: 17-Mar-2023 | D5: ESM-BY-01 | E5: Bank Yudhistira | F5: Partner 04 | G5: MT-04-ACC | H5: FR-004 | I5: AGR-004 | J5: 800000000 | K5: IDR | L5: Franchise fee payment
A6: 5 | B6: ESM-IN-005 | C6: 05-Apr-2023 | D6: ESM-BX-01 | E6: Bank Arunika | F6: Partner 05 | G6: MT-05-ACC | H6: FR-005 | I6: AGR-005 | J6: 610000000 | K6: IDR | L6: Franchise fee payment
A7: 6 | B7: ESM-IN-006 | C7: 19-Apr-2023 | D7: ESM-BY-01 | E7: Bank Yudhistira | F7: Partner 06 | G7: MT-06-ACC | H7: FR-006 | I7: AGR-006 | J7: 700000000 | K7: IDR | L7: Franchise fee payment
A8: 7 | B8: ESM-IN-007 | C8: 05-May-2023 | D8: ESM-BX-01 | E8: Bank Arunika | F8: Partner 07 | G8: MT-07-ACC | H8: FR-007 | I8: AGR-007 | J8: 560000000 | K8: IDR | L8: Franchise fee payment
A9: 8 | B9: ESM-IN-008 | C9: 22-May-2023 | D9: ESM-BY-01 | E9: Bank Yudhistira | F9: Partner 08 | G9: MT-08-ACC | H9: FR-008 | I9: AGR-008 | J9: 750000000 | K9: IDR | L9: Franchise fee payment
A10: 9 | B10: ESM-IN-009 | C10: 08-Jun-2023 | D10: ESM-BX-01 | E10: Bank Arunika | F10: Partner 09 | G10: MT-09-ACC | H10: FR-009 | I10: AGR-009 | J10: 630000000 | K10: IDR | L10: Franchise fee payment
A11: 10 | B11: ESM-IN-010 | C11: 21-Jun-2023 | D11: ESM-BY-01 | E11: Bank Yudhistira | F11: Partner 10 | G11: MT-10-ACC | H11: FR-010 | I11: AGR-010 | J11: 890000000 | K11: IDR | L11: Franchise fee payment
A12: 11 | B12: ESM-IN-011 | C12: 07-Jul-2023 | D12: ESM-BX-01 | E12: Bank Arunika | F12: Partner 11 | G12: MT-11-ACC | H12: FR-011 | I12: AGR-011 | J12: 700000000 | K12: IDR | L12: Franchise fee payment
A13: 12 | B13: ESM-IN-012 | C13: 21-Jul-2023 | D13: ESM-BY-01 | E13: Bank Yudhistira | F13: Partner 12 | G13: MT-12-ACC | H13: FR-012 | I13: AGR-012 | J13: 500000000 | K13: IDR | L13: Franchise fee payment
A14: 13 | B14: ESM-IN-013 | C14: 07-Aug-2023 | D14: ESM-BX-01 | E14: Bank Arunika | F14: Partner 13 | G14: MT-13-ACC | H14: FR-013 | I14: AGR-013 | J14: 650000000 | K14: IDR | L14: Franchise fee payment
... A41: 40 | B41: ESM-IN-040 | C41: 08-Nov-2024 | D41: ESM-BY-01 | E41: Bank Yudhistira | F41: Partner 40 | G41: MT-40-ACC | H41: FR-040 | I41: AGR-040 | J41: 720000000 | K41: IDR | L41: Franchise fee payment
